lab2/23b1045_lab2_q3/rca_Nbit.v
module half_adder(a, b, S, cout);
input a;
input b;
output S;
output cout;
wire a;
wire b;
wire S;
wire cout;
assign cout = a & b;
assign S = (a & !b) | (!a & b);
endmodule


module full_adder(a, b, cin, S, cout);
input a;
input b;
input cin;
output S;
output cout;
wire a;
wire b;
wire cin;
wire S;
wire cout;

// Internal Variables

wire s1;
wire c1;


half_adder u0(
    .a(a),
    .b(b),
    .S(s1),
    .cout(c1)
);
assign S = (s1 & !cin) | (!s1 & cin);
assign cout = c1 | (cin & a) | (cin & b);

endmodule

module rca_Nbit #(parameter N = 32) (a, b, cin, S, cout);
input [N-1:0] a, b;
input cin;
output [N-1:0] S;
output cout;
wire [N-1:0]a;
wire [N-1:0]b;
wire [N-1:0]S;
wire cout;
wire cin;

// Internal chain of carries
wire [N-1:0] cars;



full_adder init(.a(a[0]), .b(b[0]),.cin(cin), .S(S[0]), .cout(cars[0]));

generate
    genvar i;
    for (i = 1; i < N; i = i + 1) begin
        full_adder addi (.a(a[i]), .b(b[i]), .cin(cars[i-1]), .S(S[i]), .cout(cars[i]));
    end
endgenerate


assign cout = cars[N - 1];

endmodule

// Here we create a subtractor, in our case we only have situations where the
// final answer is positive so we only deal with them

module subtractor #(parameter N = 32) (a, b, S);
input [N-1:0] a, b;
output [N-1:0] S;
wire [N-1:0] a;
wire [N-1:0] b;
wire [N-1:0] S;
// Now we invert the bits of b
wire [N-1:0] b_inv;
assign b_inv = ~b;
wire temp;
wire one = 1;
rca_Nbit #(.N(N)) sub(.a(a), .b(b_inv), .cin(one), .S(S), .cout(temp));

endmodule

lab2/23b1045_lab2_q3/tb_rca_32bit.v
`timescale 1ns/1ps

module tb_rca_32_bit();

parameter N = 5;

// declare your signals as reg or wire
reg [4:0] A;
reg [4:0] B;
wire [4:0] S;
reg [4:0] true_S;




subtractor #(.N(N)) dut (.a(A), .b(B), .S(S));
initial begin	
// write the stimuli conditions
 repeat(100)
 begin
	 A = $random;
	 B = $random;
	 #5 true_S = A - B;
	 if (true_S == S) begin
		$display("Passed: A = %b, B = %b, S = %b", A, B, S);
	end
	else begin
		$display("Failed!!: A = %b, B = %b, S = %b", A, B, S);
	end

end
$finish;
end


initial begin
    $dumpfile("rca_32bit.vcd");
    $dumpvars(0, tb_rca_32_bit);
end

endmodule

lab2/23b1045_lab2_q3/rca_32bit.vcd
$date
	Sun Aug 18 19:28:25 2024
$end
$version
	Icarus Verilog
$end
$timescale
	1ps
$end
$scope module tb_rca_32_bit $end
$var wire 5 ! S [4:0] $end
$var reg 5 " A [4:0] $end
$var reg 5 # B [4:0] $end
$var reg 5 $ true_S [4:0] $end
$scope module dut $end
$var wire 5 % a [4:0] $end
$var wire 5 & b [4:0] $end
$var wire 5 ' b_inv [4:0] $end
$var wire 1 ( one $end
$var wire 1 ) temp $end
$var wire 5 * S [4:0] $end
$scope module sub $end
$var wire 5 + a [4:0] $end
$var wire 5 , b [4:0] $end
$var wire 1 ( cin $end
$var wire 1 ) cout $end
$var wire 5 - cars [4:0] $end
$var wire 5 . S [4:0] $end
$scope begin genblk1[1] $end
$scope module addi $end
$var wire 1 / S $end
$var wire 1 0 a $end
$var wire 1 1 b $end
$var wire 1 2 cin $end
$var wire 1 3 cout $end
$var wire 1 4 s1 $end
$var wire 1 5 c1 $end
$scope module u0 $end
$var wire 1 4 S $end
$var wire 1 0 a $end
$var wire 1 1 b $end
$var wire 1 5 cout $end
$upscope $end
$upscope $end
$upscope $end
$scope begin genblk1[2] $end
$scope module addi $end
$var wire 1 6 S $end
$var wire 1 7 a $end
$var wire 1 8 b $end
$var wire 1 9 cin $end
$var wire 1 : cout $end
$var wire 1 ; s1 $end
$var wire 1 < c1 $end
$scope module u0 $end
$var wire 1 ; S $end
$var wire 1 7 a $end
$var wire 1 8 b $end
$var wire 1 < cout $end
$upscope $end
$upscope $end
$upscope $end
$scope begin genblk1[3] $end
$scope module addi $end
$var wire 1 = S $end
$var wire 1 > a $end
$var wire 1 ? b $end
$var wire 1 @ cin $end
$var wire 1 A cout $end
$var wire 1 B s1 $end
$var wire 1 C c1 $end
$scope module u0 $end
$var wire 1 B S $end
$var wire 1 > a $end
$var wire 1 ? b $end
$var wire 1 C cout $end
$upscope $end
$upscope $end
$upscope $end
$scope begin genblk1[4] $end
$scope module addi $end
$var wire 1 D S $end
$var wire 1 E a $end
$var wire 1 F b $end
$var wire 1 G cin $end
$var wire 1 H cout $end
$var wire 1 I s1 $end
$var wire 1 J c1 $end
$scope module u0 $end
$var wire 1 I S $end
$var wire 1 E a $end
$var wire 1 F b $end
$var wire 1 J cout $end
$upscope $end
$upscope $end
$upscope $end
$scope module init $end
$var wire 1 K S $end
$var wire 1 L a $end
$var wire 1 M b $end
$var wire 1 ( cin $end
$var wire 1 N cout $end
$var wire 1 O s1 $end
$var wire 1 P c1 $end
$scope module u0 $end
$var wire 1 O S $end
$var wire 1 L a $end
$var wire 1 M b $end
$var wire 1 P cout $end
$upscope $end
$upscope $end
$upscope $end
$upscope $end
$upscope $end
$enddefinitions $end
#0
$dumpvars
0P
0O
0N
0M
0L
1K
0J
1I
1H
1G
1F
0E
0D
0C
1B
1A
1@
1?
0>
0=
1<
0;
1:
09
18
17
06
05
14
03
02
11
00
1/
b11 .
b11100 -
b11110 ,
b100 +
b11 *
1)
1(
b11110 '
b1 &
b100 %
bx $
b1 #
b100 "
b11 !
$end
#5000
0@
16
0=
12
b110 !
b110 *
b110 .
0K
04
0:
b11001 -
1N
1;
0B
1O
01
0<
1C
b11100 '
b11100 ,
07
1>
1L
b11 #
b11 &
b1001 "
b1001 %
b1001 +
b11 $
#10000
1)
0=
1H
0D
0/
1G
19
1A
1@
b0 !
b0 *
b0 .
06
13
14
1B
b11111 -
1:
0C
1;
11
08
0?
0<
b10010 '
b10010 ,
17
b1101 #
b1101 &
b1101 "
b1101 %
b1101 +
b110 $
#15000
1/
06
1D
1K
09
0)
b10011 !
b10011 *
b10011 .
0=
03
04
0;
b1101 -
0H
0I
0O
1<
1P
1B
01
18
1?
0F
1M
b1101 '
b1101 ,
0>
b10010 #
b10010 &
b101 "
b101 %
b101 +
b0 $
#20000
0/
1D
0K
19
0G
0)
0@
b10100 !
b10100 *
b10100 .
16
13
14
0A
0B
0H
1I
1O
b11 -
0:
0P
0;
11
08
0?
1F
0M
0<
b10010 '
b10010 ,
07
b1101 #
b1101 &
b1 "
b1 %
b1 +
b10011 $
#25000
1=
0/
1@
06
0)
1D
02
b11001 !
b11001 *
b11001 .
1K
1:
0H
b110 -
0N
04
1;
1I
0O
0F
15
0J
b10 '
b10 ,
10
17
1E
0L
b11101 #
b11101 &
b10110 "
b10110 %
b10110 +
b10100 $
#30000
1@
1:
1)
06
1H
19
0/
1G
0=
0D
12
b1 !
b1 *
b1 .
1K
13
1A
b11111 -
1N
1P
14
1B
1I
0O
1F
1M
05
b10011 '
b10011 ,
00
1>
0E
1L
b1100 #
b1100 &
b1101 "
b1101 %
b1101 +
b11001 $
#35000
1/
09
0@
06
b10011 !
b10011 *
b10011 .
1D
03
04
0B
b11001 -
0:
1C
0;
0I
01
1?
1J
b11001 '
b11001 ,
07
1E
b110 #
b110 &
b11001 "
b11001 %
b11001 +
b1 $
#40000
0)
0H
1@
1:
06
0G
1=
b11011 !
b11011 *
b11011 .
1D
b101 -
0A
1<
0;
0B
1I
18
0?
0C
0J
b10101 '
b10101 ,
17
0>
0E
b1010 #
b1010 &
b101 "
b101 %
b101 +
b10011 $
#45000
0@
16
1=
0D
b1110 !
b1110 *
b1110 .
0K
0:
0G
1;
b1 -
0A
1B
0I
1O
0<
0P
08
1?
0F
0M
b1000 '
b1000 ,
b10111 #
b10111 &
b11011 $
#50000
0=
1)
1H
09
1/
06
0D
02
b11 !
b11 *
b11 .
1K
0B
03
b10000 -
0N
1J
14
0;
0I
0O
0?
1F
b10000 '
b10000 ,
10
07
1E
0L
b1111 #
b1111 &
b10010 "
b10010 %
b10010 +
b1110 $
#55000
16
19
13
0/
b100 !
b100 *
b100 .
0K
12
b10011 -
1N
1O
1M
b10001 '
b10001 ,
b1110 #
b1110 &
b11 $
#60000
06
09
03
1G
1K
1A
02
1/
0=
1)
b11 !
b11 *
b11 .
0D
0N
0O
b11000 -
1H
1C
14
0B
1I
11
1?
0M
0J
b11010 '
b11010 ,
00
1>
0E
b101 #
b101 &
b1000 "
b1000 %
b1000 +
b100 $
#65000
0)
0H
0G
1=
b0 -
0A
16
b11111 !
b11111 *
b11111 .
1D
1B
0C
1;
1I
0?
0F
0J
b10 '
b10 ,
17
1E
b11101 #
b11101 &
b11100 "
b11100 %
b11100 +
b11 $
#70000
1@
1:
06
1)
1H
19
13
0/
1G
1=
1A
0D
12
b1000 !
b1000 *
b1000 .
0K
0B
b11111 -
1N
1C
1I
1O
1?
1F
b11010 '
b11010 ,
0E
1L
b101 #
b101 &
b1101 "
b1101 %
b1101 +
b11111 $
#75000
0)
0H
1D
1K
0/
06
0G
b11001 !
b11001 *
b11001 .
1=
0O
b111 -
0A
1P
14
1;
0B
01
18
0?
1M
05
0C
b10101 '
b10101 ,
10
07
0>
b1010 #
b1010 &
b11 "
b11 %
b11 +
b1000 $
#80000
1)
1H
0D
0=
1G
0/
b0 !
b0 *
b0 .
0K
b11111 -
1A
1B
14
1O
11
1?
0P
b11111 '
b11111 ,
00
0L
b0 #
b0 &
b0 "
b0 %
b0 +
b11001 $
#85000
0G
0A
16
0D
1K
0@
0)
02
0/
b1101 !
b1101 *
b1101 .
1=
0:
0;
0H
0I
b10 -
0N
0O
04
1B
08
0?
0F
0M
15
0C
b10 '
b10 ,
10
1>
b11101 #
b11101 &
b1010 "
b1010 %
b1010 +
b0 $
#90000
1)
1H
1G
1A
09
1/
03
1@
06
0=
b11 !
b11 *
b11 .
0D
14
b11100 -
1:
05
1<
0;
1B
1I
01
18
1?
b1100 '
b1100 ,
17
0>
1E
b10011 #
b10011 &
b10110 "
b10110 %
b10110 +
b1101 $
#95000
1/
1=
0)
1D
12
b11010 !
b11010 *
b11010 .
0K
0H
b1101 -
1N
04
0B
0I
1O
1C
00
1>
0E
1L
b1101 "
b1101 %
b1101 +
b11 $
#100000
0=
19
1/
0@
b10110 !
b10110 *
b10110 .
16
13
b1011 -
0:
15
04
0;
11
08
0<
b1010 '
b1010 ,
10
07
b10101 #
b10101 &
b1011 "
b1011 %
b1011 +
b11010 $
#105000
0/
0)
0G
0=
b10100 !
b10100 *
b10100 .
0K
14
0H
1I
b11 -
0A
05
0B
1O
01
0?
1F
1M
0C
b10001 '
b10001 ,
0>
0L
b1110 #
b1110 &
b10 "
b10 %
b10 +
b10110 $
#110000
0G
0A
09
1/
0@
16
1=
1)
0D
b1110 !
b1110 *
b1110 .
0K
03
0:
b10001 -
1H
04
1;
1B
0I
1O
0M
1J
0P
b10000 '
b10000 ,
00
17
1>
1E
1L
b1111 #
b1111 &
b11101 "
b11101 %
b11101 +
b10100 $
#115000
1@
1:
1K
19
0/
06
1=
0)
b11001 !
b11001 *
b11001 .
1D
0O
13
b111 -
0H
1P
14
1;
0B
1I
18
1M
0J
b10101 '
b10101 ,
10
07
0>
0E
b1010 #
b1010 &
b11 "
b11 %
b11 +
b1110 $
#120000
0D
1/
16
0@
0G
1=
b1110 !
b1110 *
b1110 .
0K
04
0:
0;
0I
b11 -
0A
15
1B
1O
11
08
0F
0P
b11 '
b11 ,
1>
0L
b11100 #
b11100 &
b1010 "
b1010 %
b1010 +
b11001 $
#125000
0/
06
1)
1@
1H
1=
b1000 !
b1000 *
b1000 .
0D
14
b10111 -
1:
1;
05
1J
0B
0I
01
18
1F
b10101 '
b10101 ,
0>
1E
b1010 #
b1010 &
b10010 "
b10010 %
b10010 +
b1110 $
#130000
0/
0)
0D
b1001 !
b1001 *
b1001 .
1K
b111 -
0H
14
0I
0O
11
0F
0J
1P
b111 '
b111 ,
00
0E
1L
b11000 #
b11000 &
b1 "
b1 %
b1 +
b1000 $
#135000
0@
0:
16
09
03
1/
1)
1H
0G
1=
0D
02
b1111 !
b1111 *
b1111 .
1K
0A
b10000 -
0N
1J
1B
0I
0O
1F
0M
0P
b10110 '
b10110 ,
1>
1E
0L
b1001 #
b1001 &
b11000 "
b11000 %
b11000 +
b1001 $
#140000
16
1G
0=
1A
19
0/
0)
1D
12
b10101 !
b10101 *
b10101 .
1K
0;
0B
13
0H
b1011 -
1N
1C
1P
14
0I
0O
01
08
1?
0F
1M
05
0J
b1001 '
b1001 ,
10
0E
1L
b10110 #
b10110 &
b1011 "
b1011 %
b1011 +
b1111 $
#145000
0)
1@
06
0G
1=
b11000 !
b11000 *
b11000 .
0K
0H
1I
1:
b111 -
0A
1;
0B
1O
0?
1F
0C
0P
b10001 '
b10001 ,
17
0>
0L
b1110 #
b1110 &
b110 "
b110 %
b110 +
b10101 $
#150000
09
1/
1G
0=
1)
b10010 !
b10010 *
b10010 .
1D
0;
03
1A
b11101 -
1H
1<
04
1B
0I
18
1J
b10101 '
b10101 ,
00
1>
1E
b1010 #
b1010 &
b11100 "
b11100 %
b11100 +
b11000 $
#155000
1=
19
1/
1@
06
0)
1D
b11010 !
b11010 *
b11010 .
0K
0B
13
1:
b1111 -
0H
15
1C
04
1;
0I
1O
11
1?
0F
0M
0<
0J
0P
b1110 '
b1110 ,
10
07
0E
1L
b10001 #
b10001 &
b1011 "
b1011 %
b1011 +
b10010 $
#160000
0@
0:
0)
09
1/
16
0G
b10110 !
b10110 *
b10110 .
0=
0H
1I
03
b1 -
0A
04
1;
0B
01
08
0?
1F
05
0<
0C
b10000 '
b10000 ,
00
17
0>
b1111 #
b1111 &
b101 "
b101 %
b101 +
b11010 $
#165000
1G
1A
1@
1:
1K
19
0/
06
0=
1)
b1 !
b1 *
b1 .
0D
0O
13
b11111 -
1H
1P
14
1;
1B
1I
18
0F
1M
0J
b101 '
b101 ,
10
07
1>
1E
b11010 #
b11010 &
b11011 "
b11011 %
b11011 +
b10110 $
#170000
1=
06
02
b1001 !
b1001 *
b1001 .
1K
04
0B
b11110 -
0N
15
1C
1;
0O
11
08
1?
0M
0<
0P
b1010 '
b1010 ,
17
0L
b10101 #
b10101 &
b11110 "
b11110 %
b11110 +
b1 $
#175000
0)
1@
0H
1:
1D
19
0/
06
0G
1=
12
b11000 !
b11000 *
b11000 .
0K
13
0A
b111 -
1N
14
1;
0B
1O
18
0?
05
0C
b110 '
b110 ,
00
07
0>
1L
b11001 #
b11001 &
b10001 "
b10001 %
b10001 +
b1001 $
#180000
0=
16
0@
1/
1D
b10110 !
b10110 *
b10110 .
0K
b11 -
0:
0;
04
1I
1O
08
1F
1M
15
b10011 '
b10011 ,
10
0E
0L
b1100 #
b1100 &
b10 "
b10 %
b10 +
b11000 $
#185000
1G
1A
0/
1@
06
0=
1)
1D
b10000 !
b10000 *
b10000 .
0K
14
1:
b11111 -
1H
05
1;
1B
0I
1O
01
0M
1J
0P
b10000 '
b10000 ,
17
1>
1E
1L
b1111 #
b1111 &
b11111 "
b11111 %
b11111 +
b10110 $
#190000
0D
09
0/
0@
06
02
b1 !
b1 *
b1 .
1K
0B
1I
03
0:
b11000 -
0N
1C
0J
04
0;
0O
1?
0F
b1000 '
b1000 ,
00
07
0L
b10111 #
b10111 &
b11000 "
b11000 %
b11000 +
b10000 $
#195000
1@
1)
1:
1H
0D
19
1G
0=
13
1A
1/
06
12
b11 !
b11 *
b11 .
1K
1B
b11111 -
1N
15
0C
1P
04
1;
0O
11
0?
1M
b11 '
b11 ,
10
17
1L
b11100 #
b11100 &
b11111 "
b11111 %
b11111 +
b1 $
#200000
1D
0K
b10010 !
b10010 *
b10010 .
06
0I
1O
1J
0P
1;
18
1F
0M
b10110 '
b10110 ,
07
b1001 #
b1001 &
b11011 "
b11011 %
b11011 +
b11 $
#205000
1=
1K
0/
0)
b11001 !
b11001 *
b11001 .
1D
0B
0O
b1111 -
0H
1C
1P
14
0I
1?
0F
1M
05
0J
b1111 '
b1111 ,
00
0E
b10000 #
b10000 &
b1001 "
b1001 %
b1001 +
b10010 $
#210000
0K
1/
16
0=
1)
b110 !
b110 *
b110 .
0D
1O
b11111 -
1H
0P
04
0;
1B
1I
0M
15
1<
0C
b1110 '
b1110 ,
10
17
0>
1E
b10001 #
b10001 &
b10111 "
b10111 %
b10111 +
b11001 $
#215000
06
1=
0D
0G
b1010 !
b1010 *
b1010 .
0K
1;
b10111 -
0A
0B
0I
0<
1J
1O
08
0?
1F
1M
b10011 '
b10011 ,
0L
b1100 #
b1100 &
b10110 "
b10110 %
b10110 +
b110 $
#220000
06
0)
b11010 !
b11010 *
b11010 .
1D
b111 -
0H
1;
1I
18
0J
b10111 '
b10111 ,
07
0E
b1000 #
b1000 &
b10 "
b10 %
b10 +
b1010 $
#225000
06
0)
1D
b11010 !
b11010 *
b11010 .
0K
b111 -
0H
1;
1I
1O
08
0F
0M
0<
0J
0P
b10 '
b10 ,
17
1E
1L
b11101 #
b11101 &
b10111 "
b10111 %
b10111 +
b11010 $
#230000
0=
0/
0@
16
b10100 !
b10100 *
b10100 .
0K
14
b11 -
0:
05
0;
1O
01
1M
b1 '
b1 ,
07
0L
b11110 #
b11110 &
b10010 "
b10010 %
b10010 +
#235000
1G
1A
0/
1@
16
0=
1D
b10100 !
b10100 *
b10100 .
0K
b1111 -
1:
1<
14
0;
1B
0I
1O
11
18
0M
0P
b110 '
b110 ,
00
17
1>
0E
1L
b11001 #
b11001 &
b1101 "
b1101 %
b1101 +
b10100 $
#240000
1=
0/
1)
b1100 !
b1100 *
b1100 .
0D
0B
b11111 -
1H
1C
14
1I
01
1?
05
b1100 '
b1100 ,
10
1E
b10011 #
b10011 &
b11111 "
b11111 %
b11111 +
#245000
1K
0/
0G
1=
0)
b1101 !
b1101 *
b1101 .
0D
0O
0A
b111 -
0H
1P
14
0B
0I
11
0?
1M
0C
b111 '
b111 ,
00
0>
0E
b11000 #
b11000 &
b101 "
b101 %
b101 +
b1100 $
#250000
1)
0K
1H
1/
06
1G
0=
b10010 !
b10010 *
b10010 .
1D
1O
b11111 -
1A
1J
0P
04
1;
1B
0I
1F
0M
15
0<
b10110 '
b10110 ,
10
07
1>
1E
b1001 #
b1001 &
b11011 "
b11011 %
b11011 +
b1101 $
#255000
0/
1K
b10101 !
b10101 *
b10101 .
16
14
0O
05
1P
0;
01
1M
1<
b10101 '
b10101 ,
17
b1010 #
b1010 &
b11111 "
b11111 %
b11111 +
b10010 $
#260000
09
1/
0@
06
b10010 !
b10010 *
b10010 .
0K
0B
03
b11001 -
0:
1C
04
0;
1O
08
1?
0<
0P
b11001 '
b11001 ,
00
07
0L
b110 #
b110 &
b11000 "
b11000 %
b11000 +
b10101 $
#265000
1@
1:
1G
0=
1A
19
1/
06
0)
b10010 !
b10010 *
b10010 .
1D
1B
13
b1111 -
0H
15
0C
04
1;
0I
11
0?
0F
0J
b11 '
b11 ,
10
17
0E
b11100 #
b11100 &
b1110 "
b1110 %
b1110 +
b10010 $
#270000
0/
0@
16
1)
b10100 !
b10100 *
b10100 .
1D
14
0B
0:
b11011 -
1H
05
1C
1J
0;
0I
01
1?
1F
b11001 '
b11001 ,
07
1E
b110 #
b110 &
b11010 "
b11010 %
b11010 +
#275000
1D
06
1@
1G
0=
b10000 !
b10000 *
b10000 .
0K
1:
1;
b11111 -
1A
1B
1O
18
0M
0C
0P
b11100 '
b11100 ,
0>
1L
b11 #
b11 &
b10011 "
b10011 %
b10011 +
b10100 $
#280000
16
1=
0)
b11100 !
b11100 *
b11100 .
1D
b1111 -
0H
0;
0B
0I
0F
1<
1C
0J
b1100 '
b1100 ,
17
1>
0E
b10011 #
b10011 &
b1111 "
b1111 %
b1111 +
b10000 $
#285000
1/
06
1K
1)
b11011 !
b11011 *
b11011 .
1D
04
1;
0O
b11111 -
1H
15
0<
1J
1P
0I
11
08
1F
1M
b11011 '
b11011 ,
1E
b100 #
b100 &
b11111 "
b11111 %
b11111 +
b11100 $
#290000
0D
0/
16
0K
0G
b1100 !
b1100 *
b1100 .
1=
14
0;
1O
b10111 -
0A
05
1<
0P
0B
01
18
0?
0M
0C
b10100 '
b10100 ,
0>
b1011 #
b1011 &
b10111 "
b10111 %
b10111 +
b11011 $
#295000
0)
0D
b1100 !
b1100 *
b1100 .
0K
b111 -
0H
0I
1O
0F
1M
0J
b101 '
b101 ,
0E
0L
b11010 #
b11010 &
b110 "
b110 %
b110 +
b1100 $
#300000
1D
0)
0H
0/
0@
16
0G
1=
b11100 !
b11100 *
b11100 .
0K
1I
0:
b11 -
0A
14
0;
1B
1O
11
08
1F
0M
0<
0P
b10010 '
b10010 ,
00
07
1>
1L
b1101 #
b1101 &
b1001 "
b1001 %
b1001 +
#305000
1G
0=
1A
0/
1)
1D
02
b10101 !
b10101 *
b10101 .
1K
0B
1H
b11010 -
0N
1C
04
0I
0O
1?
15
1J
b11010 '
b11010 ,
10
1E
0L
b101 #
b101 &
b11010 "
b11010 %
b11010 +
b11100 $
#310000
0)
0H
09
1/
0@
16
0G
0=
12
b10110 !
b10110 *
b10110 .
0K
1I
03
0:
0A
b1 -
1N
0J
04
1;
0B
1O
01
0?
0F
05
0C
b0 '
b0 ,
00
17
0>
1L
b11111 #
b11111 &
b10101 "
b10101 %
b10101 +
b10101 $
#315000
0/
1G
1)
1D
1K
19
1A
1H
16
b10101 !
b10101 *
b10101 .
0=
b11011 -
13
14
0I
0O
1C
1J
1P
0;
0B
11
1?
1F
1M
b11011 '
b11011 ,
07
1>
b100 #
b100 &
b11001 "
b11001 %
b11001 +
b10110 $
#320000
0D
1/
16
09
0@
0G
0=
b110 !
b110 *
b110 .
0K
03
04
0:
1;
b10001 -
0A
0B
1O
01
18
0?
0C
0P
b10101 '
b10101 ,
0>
0L
b1010 #
b1010 &
b10000 "
b10000 %
b10000 +
b10101 $
#325000
19
0/
1=
0)
1D
b11101 !
b11101 *
b11101 .
1K
0;
13
b11 -
0H
14
1B
1I
0O
08
0J
1P
b10001 '
b10001 ,
10
1>
0E
1L
b1110 #
b1110 &
b1011 "
b1011 %
b1011 +
b110 $
#330000
1G
1A
0=
09
1/
1@
06
1)
0D
b10 !
b10 *
b10 .
0K
03
1:
b11101 -
1H
1<
04
0;
1I
1O
18
0F
0J
0P
b101 '
b101 ,
00
17
1E
0L
b11010 #
b11010 &
b11100 "
b11100 %
b11100 +
b11101 $
#335000
1=
1D
b11010 !
b11010 *
b11010 .
0K
0B
0I
1C
1J
1O
1?
1F
0M
0P
b11100 '
b11100 ,
1L
b11 #
b11 &
b11101 "
b11101 %
b11101 +
b10 $
#340000
0D
1@
1:
19
0/
0G
1=
b1000 !
b1000 *
b1000 .
0K
1;
13
b10111 -
0A
0<
14
0B
1O
08
0?
1M
0C
b10001 '
b10001 ,
10
0>
0L
b1110 #
b1110 &
b10110 "
b10110 %
b10110 +
b11010 $
#345000
16
0)
1D
b11101 !
b11101 *
b11101 .
1K
0;
b111 -
0H
1<
1I
0O
18
0J
1P
b10101 '
b10101 ,
0E
1L
b1010 #
b1010 &
b111 "
b111 %
b111 +
b1000 $
#350000
1/
0)
1D
b11110 !
b11110 *
b11110 .
0K
04
b111 -
0H
15
1I
1O
11
0F
0J
0P
b111 '
b111 ,
1E
0L
b11000 #
b11000 &
b10110 "
b10110 %
b10110 +
b11101 $
#355000
1)
1H
0D
0/
06
1G
0=
b1 !
b1 *
b1 .
1K
b11111 -
1A
14
1;
1B
0O
05
0<
1P
00
07
1>
1L
b11001 "
b11001 %
b11001 +
b11110 $
#360000
09
06
0=
02
b1 !
b1 *
b1 .
1K
03
04
b11100 -
0N
0;
1B
0O
01
1?
0M
1<
0P
b1100 '
b1100 ,
17
0>
0L
b10011 #
b10011 &
b10100 "
b10100 %
b10100 +
b1 $
#365000
1/
1=
0G
0)
b1011 !
b1011 *
b1011 .
0D
14
0A
0B
b100 -
0H
0I
11
0?
b110 '
b110 ,
0E
b11001 #
b11001 &
b100 "
b100 %
b100 +
#370000
1)
1H
19
1/
0@
16
0G
1=
0D
12
b1110 !
b1110 *
b1110 .
0K
13
0:
0A
b10011 -
1N
1J
04
0;
1B
0I
1O
08
1F
15
0<
b10010 '
b10010 ,
10
07
1>
1E
1L
b1101 #
b1101 &
b11011 "
b11011 %
b11011 +
b1011 $
#375000
b1100 !
b1100 *
b1100 .
0/
14
05
00
b11001 "
b11001 %
b11001 +
b1110 $
#380000
0/
1@
16
1=
b1100 !
b1100 *
b1100 .
0K
b10111 -
1:
1<
14
0;
0B
1O
01
18
1M
05
b10101 '
b10101 ,
10
17
0>
0L
b1010 #
b1010 &
b10110 "
b10110 %
b10110 +
b1100 $
#385000
06
0=
1)
0D
b1 !
b1 *
b1 .
1K
1G
1H
02
04
1;
1A
1B
1I
b11110 -
0N
0O
15
0<
0J
11
08
1?
0F
0M
b1010 '
b1010 ,
b10101 #
b10101 &
#390000
1/
0K
12
b10 !
b10 *
b10 .
0D
b11111 -
1N
1O
1I
1F
1M
b11011 '
b11011 ,
0E
b100 #
b100 &
b110 "
b110 %
b110 +
b1 $
#395000
16
1=
0G
0D
b1110 !
b1110 *
b1110 .
0K
0;
b10111 -
0A
0B
1<
0I
1O
18
0?
0M
1J
0P
b10110 '
b10110 ,
1E
1L
b1001 #
b1001 &
b10111 "
b10111 %
b10111 +
b10 $
#400000
0/
b1100 !
b1100 *
b1100 .
0K
14
1O
1M
05
b10111 '
b10111 ,
00
0L
b1000 #
b1000 &
b10100 "
b10100 %
b10100 +
b1110 $
#405000
09
03
1/
1K
02
0@
06
0G
1=
0)
b11011 !
b11011 *
b11011 .
1D
0N
0O
0:
0A
b0 -
0H
0;
1B
1I
08
0M
0<
0J
b10010 '
b10010 ,
07
1>
0E
b1101 #
b1101 &
b1000 "
b1000 %
b1000 +
b1100 $
#410000
1@
1:
19
0/
06
1=
12
b11001 !
b11001 *
b11001 .
1K
13
b111 -
1N
1P
14
1;
0B
0O
01
1M
05
b10001 '
b10001 ,
10
17
0>
1L
b1110 #
b1110 &
b111 "
b111 %
b111 +
b11011 $
#415000
0D
0/
0@
16
0G
1=
b1100 !
b1100 *
b1100 .
0K
0I
0:
b11 -
0A
14
0;
1B
1O
11
0F
0P
b11 '
b11 ,
00
07
1>
0L
b11100 #
b11100 &
b1000 "
b1000 %
b1000 +
b11001 $
#420000
1G
1A
0=
1)
1H
1@
16
1D
b10100 !
b10100 *
b10100 .
0K
b11111 -
1:
1<
1J
0;
0I
1O
18
1F
0M
0P
b10110 '
b10110 ,
17
1E
1L
b1001 #
b1001 &
b11101 "
b11101 %
b11101 +
b1100 $
#425000
0@
0:
1/
16
0=
09
b10110 !
b10110 *
b10110 .
0K
b11001 -
03
04
1;
0B
0<
1C
1O
01
08
1?
1M
b11001 '
b11001 ,
0L
b110 #
b110 &
b11100 "
b11100 %
b11100 +
b10100 $
#430000
0)
0H
0G
1=
1D
1K
0A
02
19
0/
b11101 !
b11101 *
b11101 .
16
1B
1I
0N
0O
b10 -
13
15
0C
0J
04
0;
11
0?
0F
0M
b10 '
b10 ,
10
07
b11101 #
b11101 &
b11010 "
b11010 %
b11010 +
b10110 $
#435000
1G
1/
1A
0K
12
1@
16
0=
b10110 !
b10110 *
b10110 .
1D
1N
1O
b1111 -
1:
1<
0;
1B
0I
18
1?
1M
b1111 '
b1111 ,
17
0>
0E
b10000 #
b10000 &
b110 "
b110 %
b110 +
b11101 $
#440000
0/
1=
0G
06
0)
1D
b11001 !
b11001 *
b11001 .
1K
14
0A
0B
b111 -
0H
05
1;
1I
0O
01
0?
0<
1P
b101 '
b101 ,
07
1E
1L
b11010 #
b11010 &
b10011 "
b10011 %
b10011 +
b10110 $
#445000
1)
1H
0D
16
1G
0=
b100 !
b100 *
b100 .
0K
b11111 -
1A
0;
1B
1O
1<
0P
17
1>
0L
b11110 "
b11110 %
b11110 +
b11001 $
#450000
0)
0H
06
1D
09
1/
0G
1=
b11011 !
b11011 *
b11011 .
1K
03
b101 -
0A
04
0B
0O
1P
00
0>
1L
b10101 "
b10101 %
b10101 +
b100 $
#455000
1)
1H
0D
0K
0@
06
1G
b10 !
b10 *
b10 .
0=
1O
0:
b11001 -
1A
1C
0P
0;
0B
08
1?
0M
0<
b1000 '
b1000 ,
07
1>
b10111 #
b10111 &
b11001 "
b11001 %
b11001 +
b11011 $
#460000
1D
1@
1:
19
1/
16
1G
0=
b10110 !
b10110 *
b10110 .
0K
0I
13
b11111 -
1A
15
1<
1J
04
0;
1B
1O
11
18
1F
1M
0C
b11111 '
b11111 ,
10
17
0>
0L
b0 #
b0 &
b10110 "
b10110 %
b10110 +
b10 $
#465000
0/
06
0)
b10000 !
b10000 *
b10000 .
1D
14
1;
b1111 -
0H
05
0<
0I
01
08
0F
0J
b1001 '
b1001 ,
0E
b10110 #
b10110 &
b110 "
b110 %
b110 +
b10110 $
#470000
0/
0=
1)
0D
b1 !
b1 *
b1 .
1K
b11111 -
1H
14
1B
1I
0O
11
0?
0C
1P
b11 '
b11 ,
00
1>
1E
1L
b11100 #
b11100 &
b11101 "
b11101 %
b11101 +
b10000 $
#475000
16
1/
0G
1=
0)
0D
b1110 !
b1110 *
b1110 .
0K
0;
0A
b111 -
0H
1<
04
0B
0I
1O
18
15
0P
b111 '
b111 ,
10
0>
0E
0L
b11000 #
b11000 &
b110 "
b110 %
b110 +
b1 $
#480000
06
09
1)
03
1H
1K
02
1G
0=
b11 !
b11 *
b11 .
0D
14
0N
0O
b11100 -
1A
05
1B
1I
01
0M
b100 '
b100 ,
1>
1E
b11011 #
b11011 &
b11110 "
b11110 %
b11110 +
b1110 $
