lab2/23b1045_lab2_q1q2/cla_Nbit.v
module CLA_4bit(a, b, cin, sum, cout);
input [3:0] a;
input [3:0] b;
input cin;
wire [3:0] a;
wire [3:0] b;
wire cin;

output [3:0] sum;
output cout;
wire [3:0] sum;
wire cout;

// Internal variables
wire P0, P1, P2, P3;
wire G0, G1, G2, G3;
wire C1, C2, C3, C4;

assign P0 = a[0] ^ b[0];
assign P1 = a[1] ^ b[1];
assign P2 = a[2] ^ b[2];
assign P3 = a[3] ^ b[3];

assign G0 = a[0] & b[0];
assign G1 = a[1] & b[1];
assign G2 = a[2] & b[2];
assign G3 = a[3] & b[3];

assign C1 = G0 | (P0 & cin);
assign C2 = G1 | (P1 & G0) | (P1 & P0 & cin);
assign C3 = G2 | (P2 & G1) | (P2 & P1 & G0) | (P2 & P1 & P0 & cin);
assign C4 = G3 | (P3 & G2) | (P3 & P2 & G1) | (P3 & P2 & P1 & G0) | (P3 & P2 & P1 & P0 & cin);

assign sum[0] = P0 ^ cin;
assign sum[1] = P1 ^ C1;
assign sum[2] = P2 ^ C2;
assign sum[3] = P3 ^ C3;
assign cout = C4;



endmodule


module CLA_4bit_P_G(a, b, cin, sum, P, G);
input [3:0] a;
input [3:0] b;
input cin;
wire [3:0] a;
wire [3:0] b;
wire cin;

output [3:0] sum;
output P, G;
wire [3:0] sum;
wire P, G;
// Internal variables
wire P0, P1, P2, P3;
wire G0, G1, G2, G3;
wire C1, C2, C3;

assign P0 = a[0] ^ b[0];
assign P1 = a[1] ^ b[1];
assign P2 = a[2] ^ b[2];
assign P3 = a[3] ^ b[3];

assign G0 = a[0] & b[0];
assign G1 = a[1] & b[1];
assign G2 = a[2] & b[2];
assign G3 = a[3] & b[3];

assign C1 = G0 | (P0 & cin);
assign C2 = G1 | (P1 & G0) | (P1 & P0 & cin);
assign C3 = G2 | (P2 & G1) | (P2 & P1 & G0) | (P2 & P1 & P0 & cin);
assign G = G3 | (P3 & G2) | (P3 & P2 & G1) | (P3 & P2 & P1 & G0) | (P3 & P2 & P1 & P0 & cin);
assign P = P0 & P1 & P2 & P3;

assign sum[0] = P0 ^ cin;
assign sum[1] = P1 ^ C1;
assign sum[2] = P2 ^ C2;
assign sum[3] = P3 ^ C3;

endmodule


module lookahead_carry_unit_16_bit(P0, G0, P1, G1, P2, G2, P3, G3, cin, C4, C8, C12, C16, GF, PF);
input P0, G0, P1, G1, P2, G2, P3, G3, cin;
wire P0, G0, P1, G1, P2, G2, P3, G3, cin;
output C4, C8, C12, C16, GF, PF;
wire C4, C8, C12, C16, GF, PF;

assign PF = P0 & P1 & P2 & P3;

assign C4 = G0 | (P0 & cin);
assign C8 = G1 | (P1 & G0) | (P1 & P0 & cin);
assign C12 = G2 | (P2 & G1) | (P2 & P1 & G0) | (P2 & P1 & P0 & cin);
assign C16 = G3 | (P3 & G2) | (P3 & P2 & G1) | (P3 & P2 & P1 & G0) | (P3 & P2 & P1 & P0 & cin);
assign GF = G3 | (P3 & G2) | (P3 & P2 & G1) | (P3 & P2 & P1 & G0);
endmodule


module CLA_16bit(a, b, cin, sum, cout, Pout, Gout);
input [15:0] a;
input [15:0] b;
input cin;
wire [15:0] a;
wire [15:0] b;
wire cin;
output [15:0] sum;
output cout, Pout, Gout;
wire [15:0] sum;
wire cout, Pout, Gout;

// Internal Variables
wire C4, C8, C12, C16;
wire P0, G0, P1, G1, P2, G2, P3, G3;


CLA_4bit_P_G a0(.a(a[3:0]), .b(b[3:0]), .cin(cin), .sum(sum[3:0]), .P(P0), .G(G0));
CLA_4bit_P_G a1(.a(a[7:4]), .b(b[7:4]), .cin(C4), .sum(sum[7:4]), .P(P1), .G(G1));
CLA_4bit_P_G a2(.a(a[11:8]), .b(b[11:8]), .cin(C8), .sum(sum[11:8]), .P(P2), .G(G2));
CLA_4bit_P_G a3(.a(a[15:12]), .b(b[15:12]), .cin(C12), .sum(sum[15:12]), .P(P3), .G(G3));

lookahead_carry_unit_16_bit unit(.P0(P0), .G0(G0), .P1(P1), .G1(G1), .P2(P2), .G2(G2), .P3(P3), .G3(G3), .cin(cin), .C4(C4), .C8(C8), .C12(C12), .C16(C16), .GF(Gout), .PF(Pout));
assign cout = C16;

endmodule


module CLA_32bit(a, b, cin, sum, cout, Pout, Gout);
input [31:0] a;
input [31:0] b;
input cin;
wire [31:0] a;
wire [31:0] b;
wire cin;
output [31:0] sum;
output cout, Pout, Gout;
wire [31:0] sum;
wire cout, Pout, Gout;

// Internal Variables
wire tC16, tC32;
wire C16, C32;
wire P0, G0;
wire P1, G1;


CLA_16bit a0(.a(a[15:0]), .b(b[15:0]), .cin(cin), .sum(sum[15:0]), .cout(tC16), .Pout(P0), .Gout(G0));
CLA_16bit a1(.a(a[31:16]), .b(b[31:16]), .cin(C16), .sum(sum[31:16]), .cout(tC32), .Pout(P1), .Gout(G1));
lookahead_carry_unit_32_bit unit(.P0(P0), .G0(G0), .P1(P1), .G1(G1), .cin(cin), .C16(C16), .C32(C32), .GF(Gout), .PF(Pout));
assign cout = C32;

endmodule

module lookahead_carry_unit_32_bit (P0, G0, P1, G1, cin, C16, C32, GF, PF);
input P0, G0, P1, G1, cin;
wire P0, G0, P1, G1, cin;
output C16, C32, GF, PF;
wire C16, C32, GF, PF;

assign PF = P0 & P1;
assign C16 = G0 | (P0 & cin);
assign C32 = G1 | (P1 & G0) | (P1 & P0 & cin);
assign GF = G1 | (P1 & G0);

endmodule

lab2/23b1045_lab2_q1q2/tb_cla_32bit.v
`timescale 1ns/1ps

module tb_cla_32bit;


// declare your signals as reg or wire
reg [31:0] a;
reg [31:0] b;
reg cin;
reg [31:0] true_sum;
reg true_cout;

wire [31:0] S;
wire cout;
wire Pout;
wire Gout;

CLA_32bit dut (.a(a), .b(b), .cin(cin), .sum(S), .cout(cout), .Pout(Pout), .Gout(Gout));

initial begin
    repeat(50) begin
        a = $random;
        b = $random;
        cin = $random;
        #50;
        {true_cout, true_sum} = a + b + cin;
        #50;
        if (S !== true_sum || cout !== true_cout) begin
            $display("Error: a=%b, b=%b, cin=%b, S=%b, cout=%b, true_sum=%b, true_cout=%b", a, b, cin, S, cout, true_sum, true_cout);
            $stop;
        end
        else begin
            $display("Success: a=%b, b=%b, cin=%b, S=%b, cout=%b, true_sum=%b, true_cout=%b", a, b, cin, S, cout, true_sum, true_cout);
        end
    end
    $finish;
end



initial begin
    $dumpfile("cla_32bit.vcd");
    $dumpvars(0, tb_cla_32bit);
end

endmodule

lab2/23b1045_lab2_q1q2/cla_32bit.vcd
$date
	Wed Aug 14 01:22:13 2024
$end
$version
	Icarus Verilog
$end
$timescale
	1ps
$end
$scope module tb_cla_32bit $end
$var wire 1 ! cout $end
$var wire 32 " S [31:0] $end
$var wire 1 # Pout $end
$var wire 1 $ Gout $end
$var reg 32 % a [31:0] $end
$var reg 32 & b [31:0] $end
$var reg 1 ' cin $end
$var reg 1 ( true_cout $end
$var reg 32 ) true_sum [31:0] $end
$scope module dut $end
$var wire 32 * a [31:0] $end
$var wire 32 + b [31:0] $end
$var wire 1 ' cin $end
$var wire 1 ! cout $end
$var wire 1 , tC32 $end
$var wire 1 - tC16 $end
$var wire 32 . sum [31:0] $end
$var wire 1 # Pout $end
$var wire 1 / P1 $end
$var wire 1 0 P0 $end
$var wire 1 $ Gout $end
$var wire 1 1 G1 $end
$var wire 1 2 G0 $end
$var wire 1 3 C32 $end
$var wire 1 4 C16 $end
$scope module a0 $end
$var wire 16 5 a [15:0] $end
$var wire 16 6 b [15:0] $end
$var wire 1 ' cin $end
$var wire 1 - cout $end
$var wire 16 7 sum [15:0] $end
$var wire 1 0 Pout $end
$var wire 1 8 P3 $end
$var wire 1 9 P2 $end
$var wire 1 : P1 $end
$var wire 1 ; P0 $end
$var wire 1 2 Gout $end
$var wire 1 < G3 $end
$var wire 1 = G2 $end
$var wire 1 > G1 $end
$var wire 1 ? G0 $end
$var wire 1 @ C8 $end
$var wire 1 A C4 $end
$var wire 1 B C16 $end
$var wire 1 C C12 $end
$scope module a0 $end
$var wire 1 D C1 $end
$var wire 1 E C2 $end
$var wire 1 F C3 $end
$var wire 1 ? G $end
$var wire 1 G G0 $end
$var wire 1 H G1 $end
$var wire 1 I G2 $end
$var wire 1 J G3 $end
$var wire 1 ; P $end
$var wire 1 K P0 $end
$var wire 1 L P1 $end
$var wire 1 M P2 $end
$var wire 1 N P3 $end
$var wire 4 O a [3:0] $end
$var wire 4 P b [3:0] $end
$var wire 1 ' cin $end
$var wire 4 Q sum [3:0] $end
$upscope $end
$scope module a1 $end
$var wire 1 R C1 $end
$var wire 1 S C2 $end
$var wire 1 T C3 $end
$var wire 1 > G $end
$var wire 1 U G0 $end
$var wire 1 V G1 $end
$var wire 1 W G2 $end
$var wire 1 X G3 $end
$var wire 1 : P $end
$var wire 1 Y P0 $end
$var wire 1 Z P1 $end
$var wire 1 [ P2 $end
$var wire 1 \ P3 $end
$var wire 4 ] a [3:0] $end
$var wire 4 ^ b [3:0] $end
$var wire 4 _ sum [3:0] $end
$var wire 1 A cin $end
$upscope $end
$scope module a2 $end
$var wire 1 ` C1 $end
$var wire 1 a C2 $end
$var wire 1 b C3 $end
$var wire 1 = G $end
$var wire 1 c G0 $end
$var wire 1 d G1 $end
$var wire 1 e G2 $end
$var wire 1 f G3 $end
$var wire 1 9 P $end
$var wire 1 g P0 $end
$var wire 1 h P1 $end
$var wire 1 i P2 $end
$var wire 1 j P3 $end
$var wire 4 k a [3:0] $end
$var wire 4 l b [3:0] $end
$var wire 4 m sum [3:0] $end
$var wire 1 @ cin $end
$upscope $end
$scope module a3 $end
$var wire 1 n C1 $end
$var wire 1 o C2 $end
$var wire 1 p C3 $end
$var wire 1 < G $end
$var wire 1 q G0 $end
$var wire 1 r G1 $end
$var wire 1 s G2 $end
$var wire 1 t G3 $end
$var wire 1 8 P $end
$var wire 1 u P0 $end
$var wire 1 v P1 $end
$var wire 1 w P2 $end
$var wire 1 x P3 $end
$var wire 4 y a [3:0] $end
$var wire 4 z b [3:0] $end
$var wire 4 { sum [3:0] $end
$var wire 1 C cin $end
$upscope $end
$scope module unit $end
$var wire 1 C C12 $end
$var wire 1 B C16 $end
$var wire 1 A C4 $end
$var wire 1 @ C8 $end
$var wire 1 ? G0 $end
$var wire 1 > G1 $end
$var wire 1 = G2 $end
$var wire 1 < G3 $end
$var wire 1 2 GF $end
$var wire 1 ; P0 $end
$var wire 1 : P1 $end
$var wire 1 9 P2 $end
$var wire 1 8 P3 $end
$var wire 1 0 PF $end
$var wire 1 ' cin $end
$upscope $end
$upscope $end
$scope module a1 $end
$var wire 16 | a [15:0] $end
$var wire 16 } b [15:0] $end
$var wire 1 , cout $end
$var wire 16 ~ sum [15:0] $end
$var wire 1 4 cin $end
$var wire 1 / Pout $end
$var wire 1 !" P3 $end
$var wire 1 "" P2 $end
$var wire 1 #" P1 $end
$var wire 1 $" P0 $end
$var wire 1 1 Gout $end
$var wire 1 %" G3 $end
$var wire 1 &" G2 $end
$var wire 1 '" G1 $end
$var wire 1 (" G0 $end
$var wire 1 )" C8 $end
$var wire 1 *" C4 $end
$var wire 1 +" C16 $end
$var wire 1 ," C12 $end
$scope module a0 $end
$var wire 1 -" C1 $end
$var wire 1 ." C2 $end
$var wire 1 /" C3 $end
$var wire 1 (" G $end
$var wire 1 0" G0 $end
$var wire 1 1" G1 $end
$var wire 1 2" G2 $end
$var wire 1 3" G3 $end
$var wire 1 $" P $end
$var wire 1 4" P0 $end
$var wire 1 5" P1 $end
$var wire 1 6" P2 $end
$var wire 1 7" P3 $end
$var wire 4 8" a [3:0] $end
$var wire 4 9" b [3:0] $end
$var wire 4 :" sum [3:0] $end
$var wire 1 4 cin $end
$upscope $end
$scope module a1 $end
$var wire 1 ;" C1 $end
$var wire 1 <" C2 $end
$var wire 1 =" C3 $end
$var wire 1 '" G $end
$var wire 1 >" G0 $end
$var wire 1 ?" G1 $end
$var wire 1 @" G2 $end
$var wire 1 A" G3 $end
$var wire 1 #" P $end
$var wire 1 B" P0 $end
$var wire 1 C" P1 $end
$var wire 1 D" P2 $end
$var wire 1 E" P3 $end
$var wire 4 F" a [3:0] $end
$var wire 4 G" b [3:0] $end
$var wire 4 H" sum [3:0] $end
$var wire 1 *" cin $end
$upscope $end
$scope module a2 $end
$var wire 1 I" C1 $end
$var wire 1 J" C2 $end
$var wire 1 K" C3 $end
$var wire 1 &" G $end
$var wire 1 L" G0 $end
$var wire 1 M" G1 $end
$var wire 1 N" G2 $end
$var wire 1 O" G3 $end
$var wire 1 "" P $end
$var wire 1 P" P0 $end
$var wire 1 Q" P1 $end
$var wire 1 R" P2 $end
$var wire 1 S" P3 $end
$var wire 4 T" a [3:0] $end
$var wire 4 U" b [3:0] $end
$var wire 4 V" sum [3:0] $end
$var wire 1 )" cin $end
$upscope $end
$scope module a3 $end
$var wire 1 W" C1 $end
$var wire 1 X" C2 $end
$var wire 1 Y" C3 $end
$var wire 1 %" G $end
$var wire 1 Z" G0 $end
$var wire 1 [" G1 $end
$var wire 1 \" G2 $end
$var wire 1 ]" G3 $end
$var wire 1 !" P $end
$var wire 1 ^" P0 $end
$var wire 1 _" P1 $end
$var wire 1 `" P2 $end
$var wire 1 a" P3 $end
$var wire 4 b" a [3:0] $end
$var wire 4 c" b [3:0] $end
$var wire 4 d" sum [3:0] $end
$var wire 1 ," cin $end
$upscope $end
$scope module unit $end
$var wire 1 ," C12 $end
$var wire 1 +" C16 $end
$var wire 1 *" C4 $end
$var wire 1 )" C8 $end
$var wire 1 (" G0 $end
$var wire 1 '" G1 $end
$var wire 1 &" G2 $end
$var wire 1 %" G3 $end
$var wire 1 1 GF $end
$var wire 1 $" P0 $end
$var wire 1 #" P1 $end
$var wire 1 "" P2 $end
$var wire 1 !" P3 $end
$var wire 1 / PF $end
$var wire 1 4 cin $end
$upscope $end
$upscope $end
$scope module unit $end
$var wire 1 4 C16 $end
$var wire 1 3 C32 $end
$var wire 1 2 G0 $end
$var wire 1 1 G1 $end
$var wire 1 $ GF $end
$var wire 1 0 P0 $end
$var wire 1 / P1 $end
$var wire 1 # PF $end
$var wire 1 ' cin $end
$upscope $end
$upscope $end
$upscope $end
$enddefinitions $end
#0
$dumpvars
b1101 d"
b1100 c"
b1 b"
1a"
1`"
0_"
1^"
0]"
0\"
0["
0Z"
0Y"
0X"
0W"
b10 V"
b0 U"
b10 T"
0S"
0R"
1Q"
0P"
0O"
0N"
0M"
0L"
0K"
0J"
0I"
b1001 H"
b1000 G"
b1 F"
1E"
0D"
0C"
1B"
0A"
0@"
0?"
0>"
0="
0<"
0;"
b1110 :"
b1001 9"
b101 8"
17"
16"
05"
04"
03"
02"
01"
10"
0/"
0."
1-"
0,"
0+"
0*"
0)"
0("
0'"
0&"
0%"
0$"
0#"
0""
0!"
b1101001010011110 ~
b1100000010001001 }
b1001000010101 |
b1001 {
b101 z
b11 y
0x
1w
1v
0u
0t
0s
0r
1q
1p
1o
1n
b11 m
b1110 l
b101 k
1j
0i
1h
1g
0f
1e
0d
0c
1b
0a
0`
b1010 _
b1000 ^
b10 ]
1\
0[
1Z
0Y
0X
0W
0V
0U
0T
0S
0R
b110 Q
b1 P
b100 O
0N
1M
0L
1K
0J
0I
0H
0G
0F
0E
1D
1C
0B
0A
0@
0?
0>
1=
0<
0;
0:
09
08
b1001001110100110 7
b101111010000001 6
b11010100100100 5
04
03
02
01
00
0/
b11010010100111101001001110100110 .
0-
0,
b11000000100010010101111010000001 +
b10010000101010011010100100100 *
bx )
x(
1'
b11000000100010010101111010000001 &
b10010000101010011010100100100 %
0$
0#
b11010010100111101001001110100110 "
0!
$end
#50000
0(
b11010010100111101001001110100110 )
#100000
1K"
1J"
1I"
1A
1)"
1?
1F
1="
1'"
1E
1a
1<"
1;"
b1 Q
b111 _
b1 m
b1101000101110001 7
b1101 {
b1001 :"
0-"
b1010 H"
b1000 V"
b10111000101010011101000101110001 "
b10111000101010011101000101110001 .
b1011100010101001 ~
b1011 d"
1N
0\
1i
0e
0B"
1>"
1R"
0`"
0K
1L
1G
1[
0h
1d
0w
1s
14"
06"
00"
1D"
0E"
1?"
1A"
1P"
1_"
b1101 P
b0 ^
b1011 l
b111 z
b1011 G"
b110 U"
b0 c"
b11 O
b110 ]
b110 k
b101 y
b0 8"
b1111 F"
b1 T"
b1011 b"
b111101100001101 6
b11010111001 }
b101011001100011 5
b1011000111110000 |
b110101110010111101100001101 &
b110101110010111101100001101 +
b10110001111100000101011001100011 %
b10110001111100000101011001100011 *
#150000
b10111000101010011101000101110001 )
#200000
1!
13
0J"
0I"
1,
1+"
1$
0X"
0W"
11
0C
0A
0)"
0?
0,"
0'"
0K"
1%"
0b
0=
1/"
0="
0S
0T
0o
0p
1#"
0R
0a
1."
0<"
b1000 Q
1D
b111 _
b1001 :"
0""
b1011 V"
b11 d"
b110 m
b1101011001111000 7
b1101 {
0n
b111011111110011101011001111000 "
b111011111110011101011001111000 .
b11101111111001 ~
b1111 H"
0;"
1K
0N
0G
1Y
0g
0j
0v
16"
07"
1E"
0A"
0R"
1S"
0a"
1]"
1h
0d
1u
1w
1x
0q
0s
11"
1B"
1C"
0>"
0?"
b10 P
b1 ^
b10 l
b101 z
b111 9"
b11 G"
b1001 U"
b1000 c"
b101 O
b100 k
b1000 y
b10 8"
b1100 F"
b10 T"
b101001000010010 6
b1000100100110111 }
b1000010001100101 5
b1011001011000010 |
b10001001001101110101001000010010 &
b10001001001101110101001000010010 +
b10110010110000101000010001100101 %
b10110010110000101000010001100101 *
#250000
1(
b111011111110011101011001111000 )
#300000
1X"
1W"
0!
03
1-
1B
14
b100 d"
0,
0+"
0$
12
1,"
01
1?
1T
1S
1R
1<
1&"
b1000 _
1K"
0%"
1A
0b
1p
1J"
0""
0;
b100 Q
b1110 m
1`
b1011111010000100 7
b1011 {
b1011 :"
1-"
b1000001111110111011111010000100 "
b1000001111110111011111010000100 .
b100000111111011 ~
b1 V"
0M
1I
0h
1v
0x
1t
0Q"
1M"
1N
1j
1c
0w
1s
04"
10"
1R"
0]"
b110 P
b111 ^
b1 l
b1111 z
b11 9"
b10 G"
b1011 U"
b11 c"
b1101 O
b0 ]
b1101 k
b1100 y
b111 8"
b1101 F"
b110 T"
b0 b"
b1111000101110110 6
b11101100100011 }
b1100110100001101 5
b11011010111 |
b111011001000111111000101110110 &
b111011001000111111000101110110 +
b110110101111100110100001101 %
b110110101111100110100001101 *
#350000
0(
b1000001111110111011111010000100 )
#400000
0X"
0W"
1'"
1="
1<"
1;"
1)"
0,"
1-
1B
14
b0 H"
0C
12
1*"
1@
1("
0&"
1>
0=
1<
b1011 d"
0E
0S
0T
1b
1o
1Y"
0R
1a
0."
b1010 Q
b111 _
b1101 V"
b1111 m
b100111101111010 7
b100 {
1n
b10111101000000100100111101111010 "
b10111101000000100100111101111010 .
b1011110100000010 ~
b10 :"
1-"
0L
0N
1J
0Y
0i
1e
06"
17"
12"
0P"
0R"
0S"
1N"
1X
0j
1d
0u
1x
1q
0t
14"
00"
01"
1\"
b1100 P
b1000 ^
b111 l
b1101 9"
b110 U"
b100 c"
b1110 ]
b111 k
b101 y
b100 8"
b111 b"
b1111011110001100 6
b100011000101101 }
b101011111101101 5
b111011011010100 |
b1000110001011011111011110001100 &
b1000110001011011111011110001100 +
b1110110110101000101011111101101 %
b1110110110101000101011111101101 *
#450000
b10111101000000100100111101111010 )
#500000
0-
0B
04
1!
13
02
1,
1+"
1$
11
0*"
0("
0A
0<
0?
1%"
1T
0o
0p
0#"
0K"
1X"
b1001 m
0a
b1010 {
1."
1I"
b1000 _
0`
0n
b1110 :"
b10 H"
b110 V"
b1100011000101110 ~
b1100 d"
0[
1W
07"
0B"
1>"
0_"
1["
1L
0J
0Z
0c
0d
0q
0s
04"
10"
11"
0C"
1?"
1P"
0N"
0^"
1]"
0D
b101 P
b1100 ^
b100 l
b1000 z
b111 9"
b1111 G"
b10 U"
b1110 c"
b110 O
b1100 ]
b100 k
b10 y
b111 8"
b11 F"
b11 T"
b1110 b"
b11000110001011101010100110001011 "
b11000110001011101010100110001011 .
b1010100110001011 7
b1011 Q
b1000010011000101 6
b1110001011110111 }
b10010011000110 5
b1110001100110111 |
0'
b11100010111101111000010011000101 &
b11100010111101111000010011000101 +
b11100011001101110010010011000110 %
b11100011001101110010010011000110 *
#550000
1(
b11000110001011101010100110001011 )
#600000
1-
1B
14
1!
13
12
1,
1+"
1$
11
1@
1*"
1<
1("
1>
1="
1%"
b110 {
1/"
1Y"
1E
1p
1o
1<"
1S
1`
1a
b101 _
1-"
b1110 V"
b1100 Q
1D
b110101001011100 7
b1010 m
1n
b10 :"
b1000 H"
1;"
b101110100000100110101001011100 "
b101110100000100110101001011100 .
b10111010000010 ~
b10 d"
1W"
1Y
1\
0X
1i
0e
0v
1r
14"
16"
00"
02"
1C"
0?"
1S"
1`"
0\"
0K
1G
1V
1g
1d
1q
1s
17"
1B"
0E"
0>"
1A"
1a"
1Z"
0]"
b111 P
b111 ^
b10 l
b111 z
b10 9"
b1101 G"
b1011 U"
b1011 c"
b101 O
b1110 ]
b111 k
b1111 y
b1111 8"
b1010 F"
b10 T"
b111 b"
b111001001110111 6
b1011101111010010 }
b1111011111100101 5
b111001010101111 |
b10111011110100100111001001110111 &
b10111011110100100111001001110111 +
b1110010101011111111011111100101 %
b1110010101011111111011111100101 *
#650000
b101110100000100110101001011100 )
#700000
0!
03
1R
0,
0+"
0$
1,"
1C
0;"
01
1)"
1A
1?
0*"
1'"
1&"
0b
1=
0/"
0("
1K"
0%"
1T
1a
1S
1o
0-"
0."
1X"
0D
1n
0#"
b1 H"
b1 Q
b1000 _
b101 m
b100010110000001 7
b100 {
b1101 :"
b1 V"
b11000001000111010100010110000001 "
b11000001000111010100010110000001 .
b1100000100011101 ~
b1100 d"
1W"
1K
1M
0G
0I
0\
1X
0g
1h
1c
0d
1u
0q
0C"
1E"
1?"
0A"
1Q"
0M"
0`"
0a"
1\"
0L
1N
1H
1Z
1[
0V
0W
0i
1f
1v
0r
04"
01"
0P"
1R"
1L"
1^"
1_"
0Z"
0["
b10 P
b1111 ^
b1001 l
b110 z
b0 9"
b11 G"
b1001 U"
b111 c"
b1111 O
b1000 ]
b1011 k
b1101 y
b1100 8"
b1110 F"
b111 T"
b100 b"
b110100111110010 6
b111100100110000 }
b1101101110001111 5
b100011111101100 |
b1111001001100000110100111110010 &
b1111001001100000110100111110010 +
b1000111111011001101101110001111 %
b1000111111011001101101110001111 *
#750000
0(
b11000001000111010100010110000001 )
#800000
0-
0B
04
1!
13
02
0W"
1,
1+"
1$
11
0)"
0,"
0A
0<
1b
0F
0?
0="
0'"
1%"
0S
b1101 Q
0J"
0K"
0&"
0R
0E
0<"
b1001 m
b1100 H"
b110 V"
b1010 _
0`
b1100100110101101 7
b1100 {
b1010 :"
0I"
b11010110110010101100100110101101 "
b11010110110010101100100110101101 .
b1101011011001010 ~
b1101 d"
0Y
0h
1i
1d
15"
0B"
0S"
0H
0[
1W
0c
0x
06"
0?"
0L"
0_"
1["
1]"
b101 P
b1100 ^
b1110 l
b100 z
b1010 9"
b1100 G"
b10 U"
b1110 c"
b1000 O
b1110 ]
b1010 k
b111 y
b0 8"
b0 F"
b100 T"
b1111 b"
b100111011000101 6
b1110001011001010 }
b111101011101000 5
b1111010000000000 |
b11100010110010100100111011000101 &
b11100010110010100100111011000101 +
b11110100000000000111101011101000 %
b11110100000000000111101011101000 *
#850000
1(
b11010110110010101100100110101101 )
#900000
1,"
1R
0@
1)"
1A
1*"
1&"
1?
0>
0b
1/"
1("
1'"
1K"
0Y"
1F
0T
1p
1S
0a
1."
1J"
0X"
b0 m
b111 d"
1W"
b1110 _
b1000 {
b1001 :"
b11 H"
b111010100111001 ~
b101 V"
0N
1J
0Z
1\
1V
0X
0i
14"
1C"
0D"
0R"
1N"
0^"
1`"
1Z"
0\"
0K
0M
1G
1I
1Y
0W
0d
1w
0s
05"
16"
07"
11"
13"
0E"
1A"
0Q"
1S"
1M"
0["
1D
b1101 P
b10 ^
b1000 l
b101 z
b1011 9"
b1010 G"
b110 U"
b1001 c"
b1101 O
b1011 ]
b1000 k
b10 y
b1110 8"
b1000 F"
b1110 T"
b1101 b"
b1110101001110011000000011101011 "
b1110101001110011000000011101011 .
b1000000011101011 7
b1011 Q
b101100000101101 6
b1001011010101011 }
b10100010111101 5
b1101111010001110 |
1'
b10010110101010110101100000101101 &
b10010110101010110101100000101101 +
b11011110100011100010100010111101 %
b11011110100011100010100010111101 *
#950000
b1110101001110011000000011101011 )
#1000000
0!
03
0,
0+"
0$
0,"
01
0C
0-
0B
04
02
1*"
0A
0&"
1("
0%"
0?
1b
0=
0o
0p
0F
1="
0K"
0X"
0S
0n
1;"
1E
0R
1a
1<"
0J"
0D
b1001 m
08
b1110 {
0W"
b110 _
b10 :"
1-"
b110 H"
b111 V"
1I"
b1011011101100010 ~
b1011 d"
1K
0G
1Z
0V
1g
1i
0u
1x
17"
03"
1B"
1E"
0A"
1^"
1a"
0Z"
0]"
1N
1H
0I
0J
0Y
1[
0\
1d
0f
04"
10"
0C"
1?"
1@"
1R"
0S"
1L"
0M"
0N"
1_"
0`"
b1010 P
b0 ^
b111 l
b1000 z
b11 9"
b111 G"
b101 U"
b0 c"
b11 O
b110 ]
b10 k
b110 y
b1111 8"
b1110 F"
b1 T"
b1011 b"
b10110111011000101110100101101101 "
b10110111011000101110100101101101 .
b1110100101101101 7
b1101 Q
b1000011100001010 6
b10101110011 }
b110001001100011 5
b1011000111101111 |
0'
b101011100111000011100001010 &
b101011100111000011100001010 +
b10110001111011110110001001100011 %
b10110001111011110110001001100011 *
#1050000
0(
b10110111011000101110100101101101 )
#1100000
0;"
0)"
0*"
0'"
0b
0/"
0("
1S
0E
0a
b1100 :"
0."
b110 {
1W"
b1100 _
b110 m
1`
0-"
b1101 H"
b101 V"
0I"
b110010111011100 ~
b110 d"
0Z
1\
1V
0x
0^"
1`"
1Z"
0K
1L
0H
0[
0g
1c
0d
00"
01"
0E"
1P"
0L"
0_"
0a"
0D
b1010 ^
b101 l
b100 z
b1000 9"
b101 c"
b0 O
b10 ]
b1 k
b10 y
b100 8"
b110 F"
b0 T"
b1 b"
b1100101110111000110011011001011 "
b1100101110111000110011011001011 .
b110011011001011 7
b1011 Q
b100010110101010 6
b101010101111000 }
b10000100100000 5
b1000001100100 |
1'
b1010101011110000100010110101010 &
b1010101011110000100010110101010 +
b10000011001000010000100100000 %
b10000011001000010000100100000 *
#1150000
b1100101110111000110011011001011 )
#1200000
1!
13
1,
1+"
1$
1C
1,"
11
1F
1=
1&"
1%"
0p
0="
1J"
1D
1o
0<"
1E
b1010 _
0S
b101 d"
b1111 {
b1010 H"
b1111011010101010 7
b1010 Q
1R
0`
1n
b11 :"
b1010100101000111111011010101010 "
b1010100101000111111011010101010 .
b101010010100011 ~
b100 V"
1I"
0W"
1K
0N
0v
0w
1x
1r
14"
15"
07"
0B"
1C"
1E"
0?"
0R"
0L
1M
1H
1U
0V
1h
0c
1f
1q
06"
0@"
0P"
1Q"
1L"
1O"
0Z"
1]"
b11 P
b1 ^
b1000 l
b1011 z
b11 9"
b1000 G"
b1001 U"
b1000 c"
b110 O
b1001 ]
b1110 k
b11 y
b0 8"
b10 F"
b1011 T"
b1100 b"
b1011100000010011 6
b1000100110000011 }
b11111010010110 5
b1100101100100000 |
b10001001100000111011100000010011 &
b10001001100000111011100000010011 +
b11001011001000000011111010010110 %
b11001011001000000011111010010110 *
#1250000
1(
b1010100101000111111011010101010 )
#1300000
0!
03
0,
0+"
0$
1-
1B
14
1<"
1;"
0,"
01
1C
12
1*"
1)"
1("
0&"
0%"
0F
1=
1<
1'"
1b
1T
1p
1/"
0J"
0W"
0o
1."
1X"
0R
b1111 Q
b1011 _
b11 m
b1011001110111111 7
b1011 {
b111 :"
1-"
b100 H"
b1111 V"
b11011111010001111011001110111111 "
b11011111010001111011001110111111 .
b1101111101000111 ~
b1101 d"
1N
1Y
1Z
0U
1g
0i
1e
17"
1B"
1R"
1S"
0O"
1^"
1a"
0]"
0K
0M
1G
0\
1W
1j
0f
0x
0r
1s
1t
04"
05"
10"
11"
12"
0E"
1A"
0Q"
0`"
1["
b1011 P
b110 ^
b1101 l
b1101 z
b1111 9"
b1001 G"
b101 U"
b11 c"
b11 O
b101 ]
b110 k
b1101 y
b111 8"
b1010 F"
b1001 T"
b1010 b"
b1101110101101011 6
b11010110011111 }
b1101011001010011 5
b1010100110100111 |
b110101100111111101110101101011 &
b110101100111111101110101101011 +
b10101001101001111101011001010011 %
b10101001101001111101011001010011 *
#1350000
0(
b11011111010001111011001110111111 )
#1400000
1!
13
1,
1+"
1$
0-
0B
04
11
02
1A
0*"
0)"
1?
0("
1F
1K"
1%"
0<
0'"
1p
1J"
0T
1b
1o
0<"
1a
0X"
b1 Q
b1101 :"
0-"
b101 d"
0D
b1011 _
b1000 m
b1000100010110001 7
b1000 {
1n
b110 H"
b1011000011011011000100010110001 "
b1011000011011011000100010110001 .
b101100001101101 ~
b1000 V"
1M
1\
0g
0h
1d
1v
1w
0s
14"
07"
00"
1D"
1Q"
1`"
0a"
1]"
0G
0Y
0W
1i
0j
0e
1f
1u
0q
0t
0B"
0C"
1>"
0A"
0S"
0["
b1110 P
b1010 ^
b1110 l
b11 z
b110 9"
b101 G"
b111 U"
b1101 c"
b10 O
b0 ]
b1010 k
b100 y
b1 F"
b1 T"
b1000 b"
b11111010101110 6
b1101011101010110 }
b100101000000010 5
b1000000100010111 |
b11010111010101100011111010101110 &
b11010111010101100011111010101110 +
b10000001000101110100101000000010 %
b10000001000101110100101000000010 *
#1450000
1(
b1011000011011011000100010110001 )
