lab2/23b1045_lab2_q1q2/rca_Nbit.v
module half_adder(a, b, S, cout);
input a;
input b;
output S;
output cout;
wire a;
wire b;
wire S;
wire cout;
assign cout = a & b;
assign S = (a & !b) | (!a & b);
endmodule


module full_adder(a, b, cin, S, cout);
input a;
input b;
input cin;
output S;
output cout;
wire a;
wire b;
wire cin;
wire S;
wire cout;

// Internal Variables

wire s1;
wire c1;


half_adder u0(
    .a(a),
    .b(b),
    .S(s1),
    .cout(c1)
);
assign S = (s1 & !cin) | (!s1 & cin);
assign cout = c1 | (cin & a) | (cin & b);

endmodule

module rca_Nbit #(parameter N = 32) (a, b, cin, S, cout);
input [N-1:0] a, b;
input cin;
output [N-1:0] S;
output cout;
wire [N-1:0]a;
wire [N-1:0]b;
wire [N-1:0]S;
wire cout;
wire cin;

// Internal chain of carries
wire [N-1:0] cars;



full_adder init(.a(a[0]), .b(b[0]),.cin(cin), .S(S[0]), .cout(cars[0]));

generate
    genvar i;
    for (i = 1; i < N; i = i + 1) begin
        full_adder addi (.a(a[i]), .b(b[i]), .cin(cars[i-1]), .S(S[i]), .cout(cars[i]));
    end
endgenerate


assign cout = cars[N - 1];

endmodule

lab2/23b1045_lab2_q1q2/tb_rca_32bit.v
`timescale 1ns/1ps

module tb_rca_32_bit();

parameter N = 32;

// declare your signals as reg or wire
reg [31:0] A;
reg [31:0] B;
reg cin;
wire [31:0] S;
wire cout;
reg [31:0] true_S;
reg true_cout;




rca_Nbit #(.N(N)) dut  (.a(A), .b(B), .cin(cin), .S(S), .cout(cout));
initial begin	
// write the stimuli conditions
 repeat(100)
 begin
	 A = $random;
	 B = $random;
	 cin = $random;
	 #5 {true_cout, true_S} = A + B + cin;
	 if (true_cout == cout && true_S == S) begin
		$display("Passed: A = %b, B = %b, cin = %b, cout = %b, S = %b", A, B, cin, cout, S);
	end
	else begin
		$display("Failed!!: A = %b, B = %b, cin = %b, cout = %b, S = %b", A, B, cin, cout, S);
	end

end
$finish;
end


initial begin
    $dumpfile("rca_32bit.vcd");
    $dumpvars(0, tb_rca_32_bit);
end

endmodule

lab2/23b1045_lab2_q1q2/rca_32bit.vcd
$date
	Tue Aug 13 21:01:57 2024
$end
$version
	Icarus Verilog
$end
$timescale
	1ps
$end
$scope module tb_rca_32_bit $end
$var wire 1 ! cout $end
$var wire 32 " S [31:0] $end
$var reg 32 # A [31:0] $end
$var reg 32 $ B [31:0] $end
$var reg 1 % cin $end
$var reg 32 & true_S [31:0] $end
$var reg 1 ' true_cout $end
$scope module dut $end
$var wire 32 ( a [31:0] $end
$var wire 32 ) b [31:0] $end
$var wire 1 % cin $end
$var wire 1 ! cout $end
$var wire 32 * cars [31:0] $end
$var wire 32 + S [31:0] $end
$scope begin genblk1[1] $end
$scope module addi $end
$var wire 1 , S $end
$var wire 1 - a $end
$var wire 1 . b $end
$var wire 1 / cin $end
$var wire 1 0 cout $end
$var wire 1 1 s1 $end
$var wire 1 2 c1 $end
$scope module u0 $end
$var wire 1 1 S $end
$var wire 1 - a $end
$var wire 1 . b $end
$var wire 1 2 cout $end
$upscope $end
$upscope $end
$upscope $end
$scope begin genblk1[2] $end
$scope module addi $end
$var wire 1 3 S $end
$var wire 1 4 a $end
$var wire 1 5 b $end
$var wire 1 6 cin $end
$var wire 1 7 cout $end
$var wire 1 8 s1 $end
$var wire 1 9 c1 $end
$scope module u0 $end
$var wire 1 8 S $end
$var wire 1 4 a $end
$var wire 1 5 b $end
$var wire 1 9 cout $end
$upscope $end
$upscope $end
$upscope $end
$scope begin genblk1[3] $end
$scope module addi $end
$var wire 1 : S $end
$var wire 1 ; a $end
$var wire 1 < b $end
$var wire 1 = cin $end
$var wire 1 > cout $end
$var wire 1 ? s1 $end
$var wire 1 @ c1 $end
$scope module u0 $end
$var wire 1 ? S $end
$var wire 1 ; a $end
$var wire 1 < b $end
$var wire 1 @ cout $end
$upscope $end
$upscope $end
$upscope $end
$scope begin genblk1[4] $end
$scope module addi $end
$var wire 1 A S $end
$var wire 1 B a $end
$var wire 1 C b $end
$var wire 1 D cin $end
$var wire 1 E cout $end
$var wire 1 F s1 $end
$var wire 1 G c1 $end
$scope module u0 $end
$var wire 1 F S $end
$var wire 1 B a $end
$var wire 1 C b $end
$var wire 1 G cout $end
$upscope $end
$upscope $end
$upscope $end
$scope begin genblk1[5] $end
$scope module addi $end
$var wire 1 H S $end
$var wire 1 I a $end
$var wire 1 J b $end
$var wire 1 K cin $end
$var wire 1 L cout $end
$var wire 1 M s1 $end
$var wire 1 N c1 $end
$scope module u0 $end
$var wire 1 M S $end
$var wire 1 I a $end
$var wire 1 J b $end
$var wire 1 N cout $end
$upscope $end
$upscope $end
$upscope $end
$scope begin genblk1[6] $end
$scope module addi $end
$var wire 1 O S $end
$var wire 1 P a $end
$var wire 1 Q b $end
$var wire 1 R cin $end
$var wire 1 S cout $end
$var wire 1 T s1 $end
$var wire 1 U c1 $end
$scope module u0 $end
$var wire 1 T S $end
$var wire 1 P a $end
$var wire 1 Q b $end
$var wire 1 U cout $end
$upscope $end
$upscope $end
$upscope $end
$scope begin genblk1[7] $end
$scope module addi $end
$var wire 1 V S $end
$var wire 1 W a $end
$var wire 1 X b $end
$var wire 1 Y cin $end
$var wire 1 Z cout $end
$var wire 1 [ s1 $end
$var wire 1 \ c1 $end
$scope module u0 $end
$var wire 1 [ S $end
$var wire 1 W a $end
$var wire 1 X b $end
$var wire 1 \ cout $end
$upscope $end
$upscope $end
$upscope $end
$scope begin genblk1[8] $end
$scope module addi $end
$var wire 1 ] S $end
$var wire 1 ^ a $end
$var wire 1 _ b $end
$var wire 1 ` cin $end
$var wire 1 a cout $end
$var wire 1 b s1 $end
$var wire 1 c c1 $end
$scope module u0 $end
$var wire 1 b S $end
$var wire 1 ^ a $end
$var wire 1 _ b $end
$var wire 1 c cout $end
$upscope $end
$upscope $end
$upscope $end
$scope begin genblk1[9] $end
$scope module addi $end
$var wire 1 d S $end
$var wire 1 e a $end
$var wire 1 f b $end
$var wire 1 g cin $end
$var wire 1 h cout $end
$var wire 1 i s1 $end
$var wire 1 j c1 $end
$scope module u0 $end
$var wire 1 i S $end
$var wire 1 e a $end
$var wire 1 f b $end
$var wire 1 j cout $end
$upscope $end
$upscope $end
$upscope $end
$scope begin genblk1[10] $end
$scope module addi $end
$var wire 1 k S $end
$var wire 1 l a $end
$var wire 1 m b $end
$var wire 1 n cin $end
$var wire 1 o cout $end
$var wire 1 p s1 $end
$var wire 1 q c1 $end
$scope module u0 $end
$var wire 1 p S $end
$var wire 1 l a $end
$var wire 1 m b $end
$var wire 1 q cout $end
$upscope $end
$upscope $end
$upscope $end
$scope begin genblk1[11] $end
$scope module addi $end
$var wire 1 r S $end
$var wire 1 s a $end
$var wire 1 t b $end
$var wire 1 u cin $end
$var wire 1 v cout $end
$var wire 1 w s1 $end
$var wire 1 x c1 $end
$scope module u0 $end
$var wire 1 w S $end
$var wire 1 s a $end
$var wire 1 t b $end
$var wire 1 x cout $end
$upscope $end
$upscope $end
$upscope $end
$scope begin genblk1[12] $end
$scope module addi $end
$var wire 1 y S $end
$var wire 1 z a $end
$var wire 1 { b $end
$var wire 1 | cin $end
$var wire 1 } cout $end
$var wire 1 ~ s1 $end
$var wire 1 !" c1 $end
$scope module u0 $end
$var wire 1 ~ S $end
$var wire 1 z a $end
$var wire 1 { b $end
$var wire 1 !" cout $end
$upscope $end
$upscope $end
$upscope $end
$scope begin genblk1[13] $end
$scope module addi $end
$var wire 1 "" S $end
$var wire 1 #" a $end
$var wire 1 $" b $end
$var wire 1 %" cin $end
$var wire 1 &" cout $end
$var wire 1 '" s1 $end
$var wire 1 (" c1 $end
$scope module u0 $end
$var wire 1 '" S $end
$var wire 1 #" a $end
$var wire 1 $" b $end
$var wire 1 (" cout $end
$upscope $end
$upscope $end
$upscope $end
$scope begin genblk1[14] $end
$scope module addi $end
$var wire 1 )" S $end
$var wire 1 *" a $end
$var wire 1 +" b $end
$var wire 1 ," cin $end
$var wire 1 -" cout $end
$var wire 1 ." s1 $end
$var wire 1 /" c1 $end
$scope module u0 $end
$var wire 1 ." S $end
$var wire 1 *" a $end
$var wire 1 +" b $end
$var wire 1 /" cout $end
$upscope $end
$upscope $end
$upscope $end
$scope begin genblk1[15] $end
$scope module addi $end
$var wire 1 0" S $end
$var wire 1 1" a $end
$var wire 1 2" b $end
$var wire 1 3" cin $end
$var wire 1 4" cout $end
$var wire 1 5" s1 $end
$var wire 1 6" c1 $end
$scope module u0 $end
$var wire 1 5" S $end
$var wire 1 1" a $end
$var wire 1 2" b $end
$var wire 1 6" cout $end
$upscope $end
$upscope $end
$upscope $end
$scope begin genblk1[16] $end
$scope module addi $end
$var wire 1 7" S $end
$var wire 1 8" a $end
$var wire 1 9" b $end
$var wire 1 :" cin $end
$var wire 1 ;" cout $end
$var wire 1 <" s1 $end
$var wire 1 =" c1 $end
$scope module u0 $end
$var wire 1 <" S $end
$var wire 1 8" a $end
$var wire 1 9" b $end
$var wire 1 =" cout $end
$upscope $end
$upscope $end
$upscope $end
$scope begin genblk1[17] $end
$scope module addi $end
$var wire 1 >" S $end
$var wire 1 ?" a $end
$var wire 1 @" b $end
$var wire 1 A" cin $end
$var wire 1 B" cout $end
$var wire 1 C" s1 $end
$var wire 1 D" c1 $end
$scope module u0 $end
$var wire 1 C" S $end
$var wire 1 ?" a $end
$var wire 1 @" b $end
$var wire 1 D" cout $end
$upscope $end
$upscope $end
$upscope $end
$scope begin genblk1[18] $end
$scope module addi $end
$var wire 1 E" S $end
$var wire 1 F" a $end
$var wire 1 G" b $end
$var wire 1 H" cin $end
$var wire 1 I" cout $end
$var wire 1 J" s1 $end
$var wire 1 K" c1 $end
$scope module u0 $end
$var wire 1 J" S $end
$var wire 1 F" a $end
$var wire 1 G" b $end
$var wire 1 K" cout $end
$upscope $end
$upscope $end
$upscope $end
$scope begin genblk1[19] $end
$scope module addi $end
$var wire 1 L" S $end
$var wire 1 M" a $end
$var wire 1 N" b $end
$var wire 1 O" cin $end
$var wire 1 P" cout $end
$var wire 1 Q" s1 $end
$var wire 1 R" c1 $end
$scope module u0 $end
$var wire 1 Q" S $end
$var wire 1 M" a $end
$var wire 1 N" b $end
$var wire 1 R" cout $end
$upscope $end
$upscope $end
$upscope $end
$scope begin genblk1[20] $end
$scope module addi $end
$var wire 1 S" S $end
$var wire 1 T" a $end
$var wire 1 U" b $end
$var wire 1 V" cin $end
$var wire 1 W" cout $end
$var wire 1 X" s1 $end
$var wire 1 Y" c1 $end
$scope module u0 $end
$var wire 1 X" S $end
$var wire 1 T" a $end
$var wire 1 U" b $end
$var wire 1 Y" cout $end
$upscope $end
$upscope $end
$upscope $end
$scope begin genblk1[21] $end
$scope module addi $end
$var wire 1 Z" S $end
$var wire 1 [" a $end
$var wire 1 \" b $end
$var wire 1 ]" cin $end
$var wire 1 ^" cout $end
$var wire 1 _" s1 $end
$var wire 1 `" c1 $end
$scope module u0 $end
$var wire 1 _" S $end
$var wire 1 [" a $end
$var wire 1 \" b $end
$var wire 1 `" cout $end
$upscope $end
$upscope $end
$upscope $end
$scope begin genblk1[22] $end
$scope module addi $end
$var wire 1 a" S $end
$var wire 1 b" a $end
$var wire 1 c" b $end
$var wire 1 d" cin $end
$var wire 1 e" cout $end
$var wire 1 f" s1 $end
$var wire 1 g" c1 $end
$scope module u0 $end
$var wire 1 f" S $end
$var wire 1 b" a $end
$var wire 1 c" b $end
$var wire 1 g" cout $end
$upscope $end
$upscope $end
$upscope $end
$scope begin genblk1[23] $end
$scope module addi $end
$var wire 1 h" S $end
$var wire 1 i" a $end
$var wire 1 j" b $end
$var wire 1 k" cin $end
$var wire 1 l" cout $end
$var wire 1 m" s1 $end
$var wire 1 n" c1 $end
$scope module u0 $end
$var wire 1 m" S $end
$var wire 1 i" a $end
$var wire 1 j" b $end
$var wire 1 n" cout $end
$upscope $end
$upscope $end
$upscope $end
$scope begin genblk1[24] $end
$scope module addi $end
$var wire 1 o" S $end
$var wire 1 p" a $end
$var wire 1 q" b $end
$var wire 1 r" cin $end
$var wire 1 s" cout $end
$var wire 1 t" s1 $end
$var wire 1 u" c1 $end
$scope module u0 $end
$var wire 1 t" S $end
$var wire 1 p" a $end
$var wire 1 q" b $end
$var wire 1 u" cout $end
$upscope $end
$upscope $end
$upscope $end
$scope begin genblk1[25] $end
$scope module addi $end
$var wire 1 v" S $end
$var wire 1 w" a $end
$var wire 1 x" b $end
$var wire 1 y" cin $end
$var wire 1 z" cout $end
$var wire 1 {" s1 $end
$var wire 1 |" c1 $end
$scope module u0 $end
$var wire 1 {" S $end
$var wire 1 w" a $end
$var wire 1 x" b $end
$var wire 1 |" cout $end
$upscope $end
$upscope $end
$upscope $end
$scope begin genblk1[26] $end
$scope module addi $end
$var wire 1 }" S $end
$var wire 1 ~" a $end
$var wire 1 !# b $end
$var wire 1 "# cin $end
$var wire 1 ## cout $end
$var wire 1 $# s1 $end
$var wire 1 %# c1 $end
$scope module u0 $end
$var wire 1 $# S $end
$var wire 1 ~" a $end
$var wire 1 !# b $end
$var wire 1 %# cout $end
$upscope $end
$upscope $end
$upscope $end
$scope begin genblk1[27] $end
$scope module addi $end
$var wire 1 &# S $end
$var wire 1 '# a $end
$var wire 1 (# b $end
$var wire 1 )# cin $end
$var wire 1 *# cout $end
$var wire 1 +# s1 $end
$var wire 1 ,# c1 $end
$scope module u0 $end
$var wire 1 +# S $end
$var wire 1 '# a $end
$var wire 1 (# b $end
$var wire 1 ,# cout $end
$upscope $end
$upscope $end
$upscope $end
$scope begin genblk1[28] $end
$scope module addi $end
$var wire 1 -# S $end
$var wire 1 .# a $end
$var wire 1 /# b $end
$var wire 1 0# cin $end
$var wire 1 1# cout $end
$var wire 1 2# s1 $end
$var wire 1 3# c1 $end
$scope module u0 $end
$var wire 1 2# S $end
$var wire 1 .# a $end
$var wire 1 /# b $end
$var wire 1 3# cout $end
$upscope $end
$upscope $end
$upscope $end
$scope begin genblk1[29] $end
$scope module addi $end
$var wire 1 4# S $end
$var wire 1 5# a $end
$var wire 1 6# b $end
$var wire 1 7# cin $end
$var wire 1 8# cout $end
$var wire 1 9# s1 $end
$var wire 1 :# c1 $end
$scope module u0 $end
$var wire 1 9# S $end
$var wire 1 5# a $end
$var wire 1 6# b $end
$var wire 1 :# cout $end
$upscope $end
$upscope $end
$upscope $end
$scope begin genblk1[30] $end
$scope module addi $end
$var wire 1 ;# S $end
$var wire 1 <# a $end
$var wire 1 =# b $end
$var wire 1 ># cin $end
$var wire 1 ?# cout $end
$var wire 1 @# s1 $end
$var wire 1 A# c1 $end
$scope module u0 $end
$var wire 1 @# S $end
$var wire 1 <# a $end
$var wire 1 =# b $end
$var wire 1 A# cout $end
$upscope $end
$upscope $end
$upscope $end
$scope begin genblk1[31] $end
$scope module addi $end
$var wire 1 B# S $end
$var wire 1 C# a $end
$var wire 1 D# b $end
$var wire 1 E# cin $end
$var wire 1 F# cout $end
$var wire 1 G# s1 $end
$var wire 1 H# c1 $end
$scope module u0 $end
$var wire 1 G# S $end
$var wire 1 C# a $end
$var wire 1 D# b $end
$var wire 1 H# cout $end
$upscope $end
$upscope $end
$upscope $end
$scope module init $end
$var wire 1 I# S $end
$var wire 1 J# a $end
$var wire 1 K# b $end
$var wire 1 % cin $end
$var wire 1 L# cout $end
$var wire 1 M# s1 $end
$var wire 1 N# c1 $end
$scope module u0 $end
$var wire 1 M# S $end
$var wire 1 J# a $end
$var wire 1 K# b $end
$var wire 1 N# cout $end
$upscope $end
$upscope $end
$upscope $end
$upscope $end
$enddefinitions $end
#0
$dumpvars
0N#
1M#
1L#
1K#
0J#
0I#
0H#
1G#
0F#
0E#
1D#
0C#
1B#
0A#
1@#
0?#
0>#
1=#
0<#
1;#
0:#
09#
08#
07#
06#
05#
04#
03#
12#
01#
00#
0/#
1.#
1-#
0,#
0+#
0*#
0)#
0(#
0'#
0&#
0%#
0$#
0##
0"#
0!#
0~"
0}"
0|"
1{"
0z"
0y"
0x"
1w"
1v"
0u"
0t"
0s"
0r"
0q"
0p"
0o"
0n"
1m"
0l"
0k"
1j"
0i"
1h"
0g"
0f"
0e"
0d"
0c"
0b"
0a"
0`"
0_"
0^"
0]"
0\"
0["
0Z"
0Y"
1X"
0W"
0V"
0U"
1T"
1S"
0R"
1Q"
0P"
0O"
1N"
0M"
1L"
0K"
1J"
0I"
0H"
0G"
1F"
1E"
0D"
0C"
0B"
1A"
0@"
0?"
1>"
1="
0<"
1;"
0:"
19"
18"
07"
06"
05"
04"
13"
02"
01"
10"
0/"
1."
1-"
1,"
1+"
0*"
0)"
0("
1'"
1&"
1%"
0$"
1#"
0""
1!"
0~
1}
1|
1{
1z
1y
0x
1w
1v
1u
1t
0s
0r
1q
0p
1o
0n
1m
1l
0k
0j
1i
0h
0g
1f
0e
1d
0c
1b
0a
0`
0_
1^
1]
0\
1[
0Z
0Y
1X
0W
1V
0U
0T
0S
0R
0Q
0P
0O
0N
1M
0L
0K
0J
1I
1H
0G
0F
0E
0D
0C
0B
0A
0@
0?
0>
0=
0<
0;
0:
09
18
07
06
05
14
13
02
01
00
1/
0.
0-
1,
b11010010100111101001001110100110 +
b10111110000000001 *
b11000000100010010101111010000001 )
b10010000101010011010100100100 (
x'
bx &
1%
b11000000100010010101111010000001 $
b10010000101010011010100100100 #
b11010010100111101001001110100110 "
0!
$end
#5000
1&#
1)#
1##
1A
1"#
1D
1z"
0v"
1y
1>
1k"
1y"
1|
1=
1e"
1s"
1v
0r
1Z"
17
03
0>"
0:
0V
1u
0k
1]"
0S"
0}"
0;#
16
0,
1O
1n
0d
1)"
0A"
17"
0E"
1d"
0a"
1r"
1h"
0o"
14#
b10111000101010011101000101110001 "
b10111000101010011101000101110001 +
1I#
1o
1W"
10
1h
0;"
1^"
b111111100000111111000001111 *
1l"
1?
0[
1p
0X"
1$#
0@#
11
1T
0i
0."
1<"
0J"
1f"
0m"
1t"
19#
0M#
0q
1Y"
1j
1/"
0="
1`"
1n"
1N#
15
1<
0X
1_
0m
1$"
1U"
1\"
1x"
1!#
0=#
0D#
1-
04
1P
0^
1e
0#"
1*"
08"
0F"
1["
1b"
1i"
1p"
0w"
15#
1C#
1J#
b110101110010111101100001101 $
b110101110010111101100001101 )
b10110001111100000101011001100011 #
b10110001111100000101011001100011 (
0'
b11010010100111101001001110100110 &
#10000
0"#
0z"
1v"
0y"
0s"
1o"
0r"
0l"
0V
0;#
0Y
0>#
0k"
0S
08#
0e"
1O
14#
0>"
1a"
0u
0R
07#
0o
0A"
1O"
0d"
0L
0%"
03"
01#
1k
0;"
17"
1I"
0^"
1H
0}
0-"
1-#
1:
1A
0]
0r
0""
0E"
1L"
1h"
0}"
1&#
1!
0B#
0I#
0n
1d
1y
1)"
0:"
10"
1H"
0]"
1S"
b111011111110011101011001111000 "
b111011111110011101011001111000 +
1Z"
0D
0K
0|
0,"
0)#
00#
1F#
0h
04"
1B"
0W"
0>
0?
0E
1F
0b
0v
0w
0&"
0'"
1J"
0Q"
1m"
0##
0$#
b10000000000001100000000000000111 *
0*#
1+#
0G#
1M#
1i
1~
1."
15"
1X"
1_"
0n"
1H#
0N#
0j
0!"
0/"
1D"
0Y"
0`"
1.
05
0<
1C
0_
0t
0$"
1@"
1G"
0N"
0j"
1q"
0x"
0!#
1(#
1D#
0K#
0-
14
0e
0z
0*"
11"
1?"
0T"
0["
0p"
1w"
b10001001001101110101001000010010 $
b10001001001101110101001000010010 )
b10110010110000101000010001100101 #
b10110010110000101000010001100101 (
b10111000101010011101000101110001 &
#15000
1;#
1>#
18#
04#
1V
17#
11#
0-#
1Y
1S
0O
10#
1*#
0&#
1R
1L
0H
1)#
1##
1K
1E
0A
1>"
13
1d
1""
1:"
10"
1"#
0v"
1D
0:
1g
1r
13"
0)"
1A"
17"
b1000001111110111011111010000100 "
b1000001111110111011111010000100 +
0}"
0!
14"
1z"
1>
1a
1-"
1;"
b111110000001111100000101111111 *
0F#
08
0i
1'"
05"
0{"
1?
1w
0."
0<"
1$#
19
16"
1|"
1c
1/"
1="
0H#
15
1J
1Q
1_
0f
1$"
12"
0G"
0U"
1x"
1/#
16#
0D#
1;
0I
0P
1^
1s
1*"
18"
1F"
1T"
1~"
0.#
05#
0C#
b111011001000111111000101110110 $
b111011001000111111000101110110 )
b110110101111100110100001101 #
b110110101111100110100001101 (
1'
b111011111110011101011001111000 &
#20000
1r"
1l"
0h"
1k"
0V
1e"
0;#
0a"
0Y
0>#
0S
1d"
08#
1O
1^"
0Z"
14#
1)"
0R
1]"
07#
1,"
0L
1W"
01#
1&"
0""
03
1H
1]
0S"
1-#
1B#
1,
1:
1A
1u
1k
0E"
0L"
1o"
1}"
1&#
1r
1%"
0y
00"
b10111101000000100100111101111010 "
b10111101000000100100111101111010 +
07"
06
0K
1`
1n
1o
0H"
1V"
00#
1E#
1}
00
01
0?
0E
0F
1Z
1h
0p
0B"
0J"
1P"
1Q"
0t"
0$#
0*#
0+#
b1000110111111011111011110001101 *
1?#
0w
0~
15"
1<"
1@
1q
1K"
1%#
1\
1j
1!"
06"
0="
0D"
1A#
0.
1<
0C
0J
0Q
1X
1f
1m
0@"
1G"
1N"
0q"
1!#
0(#
0/#
06#
1=#
1I
1P
1W
1e
0s
1z
01"
08"
0?"
1.#
15#
1<#
b1000110001011011111011110001100 $
b1000110001011011111011110001100 )
b1110110110101000101011111101101 #
b1110110110101000101011111101101 (
0'
b1000001111110111011111010000100 &
#25000
0)"
0,"
0&"
1V
0:"
1;#
03
1""
1v"
0A
0d
0k
04"
10"
1E"
0&#
1Y
0O
1L"
0S"
1>#
04#
06
1,
0H
0%"
07"
1Z"
1y"
0o"
0-#
0/
0D
1S
0g
0n
03"
1H"
0V"
0)#
18#
1!
00
0}
1s"
0L#
0>
0T
0a
0h
0-"
1B"
0P"
0Q"
0X"
0##
09#
b11100011111101110000010011000100 *
1F#
11
0M
0<"
0_"
1t"
02#
b11000110001011101010100110001011 "
b11000110001011101010100110001011 +
1I#
1U
1Y"
1:#
0@
0c
0j
0!"
0/"
1="
1D"
1`"
0%#
1H#
0<
1Q
0_
0f
0{
0$"
0+"
1@"
0N"
1U"
1c"
1j"
0!#
16#
1D#
1K#
1-
0;
0I
0^
0e
0z
1#"
0*"
18"
1?"
1["
0b"
0i"
1p"
0~"
0.#
1C#
0J#
0%
b11100010111101111000010011000101 $
b11100010111101111000010011000101 )
b11100011001101110010010011000110 #
b11100011001101110010010011000110 (
b10111101000000100100111101111010 &
#30000
1k"
1e"
0a"
13
1:"
1d"
14"
1^"
16
1r
1)"
1>"
1O
1d
00"
14#
10
0,
1A
0V
1u
0k
1,"
1""
1A"
07"
0E"
0Z"
1&#
0;#
1R
1g
0]
1n
1%"
13"
1V"
0L"
1]"
0S"
1h"
17#
0B#
1/
b101110100000100110101001011100 "
b101110100000100110101001011100 +
0I#
1o
1&"
1;"
1L
1a
1h
1}
1-"
1P"
1W"
11#
b11110011111111111111011111100111 *
1L#
1F
1[
1p
0'"
1<"
1J"
1_"
1+#
1@#
1b
1Q"
1X"
0m"
1G#
0M#
0\
0q
1("
0="
0K"
0`"
0A#
1N
1j
1!"
1/"
0Y"
1n"
13#
0H#
1N#
1.
1C
1J
0X
1f
0m
1{
1$"
1+"
02"
09"
0G"
0\"
1q"
1(#
1/#
0=#
0-
1I
1^
1e
1z
1*"
11"
1M"
0T"
1i"
0p"
1.#
0C#
1J#
b10111011110100100111001001110111 $
b10111011110100100111001001110111 )
b1110010101011111111011111100101 #
b1110010101011111111011111100101 (
1'
b11000110001011101010100110001011 &
#35000
0]"
0W"
1S"
0V"
0P"
1)"
1L"
1,"
0O"
1K
1Y
10#
1>#
1&"
0I"
1E
0A
1S
0r
0>"
1*#
0&#
18#
1E"
03
1V
1]
0d
1%"
0y
0Z"
0h"
0v"
1;#
1B#
0/
1I#
0,
1D
0:
1R
0H
0O
0u
1k
0""
0A"
17"
1o"
1)#
0}"
17#
0-#
b11000001000111010100010110000001 "
b11000001000111010100010110000001 +
04#
1|
1}
0H"
0!
0L#
1>
1L
0o
0;"
1##
11#
18
0[
0b
1i
1v
1~
0B"
0_"
1m"
1{"
0@#
b1111111111000001111101111111110 *
0F#
0G#
1M#
01
1?
1M
1T
0p
1'"
0<"
0t"
1$#
12#
19#
09
1\
1c
0j
0!"
1`"
0n"
0|"
1A#
0N#
12
0N
0U
1x
0("
0D"
1u"
03#
0:#
05
1X
1_
0f
1t
0{
0@"
1\"
0c"
0j"
0x"
1=#
0D#
0K#
1-
1;
0I
0P
0l
1s
0#"
08"
0?"
1b"
1p"
1~"
0.#
05#
b1111001001100000110100111110010 $
b1111001001100000110100111110010 )
b1000111111011001101101110001111 #
b1000111111011001101101110001111 (
b101110100000100110101001011100 &
#40000
0o"
0D
0)#
0>
0r"
0##
1:
0l"
1h"
1}"
0R
07#
0=
0k"
0L
0"#
01#
07
13
07"
0e"
1a"
1H
1r
0z"
1v"
1-#
0A
0d
0k
1>"
0S"
0&#
06
0O
0:"
10"
0E"
0d"
b11010110110010101100100110101101 "
b11010110110010101100100110101101 +
04#
0K
0g
1u
0y"
00#
1!
00
04"
0^"
0E
0F
0a
0i
1o
1p
1C"
0X"
0s"
0*#
0+#
b11100000000000000111111011000000 *
1F#
0T
05"
0J"
09#
1j
02
1U
0c
0`"
0u"
1:#
1H#
0.
15
0C
0J
0_
1f
1m
0$"
1@"
1N"
0U"
0\"
1c"
1j"
0q"
1x"
0(#
0/#
1D#
1K#
0-
04
1I
1P
0^
1#"
01"
0F"
0M"
0["
0b"
0i"
0p"
0w"
1.#
15#
1C#
0J#
b11100010110010100100111011000101 $
b11100010110010100100111011000101 )
b11110100000000000111101011101000 #
b11110100000000000111101011101000 (
0'
b11000001000111010100010110000001 &
#45000
0]
0B#
1K
10#
0`
1O"
0E#
1E
1*#
0Z
1I"
0?#
1O
14#
1S"
1o"
0r
1,
1D
1:
1R
1H
1V
0k
17"
1Z"
0a"
1)#
1}"
17#
1-#
1;#
1=
03
0A
0Y
0n
0)"
1H"
0>"
0E"
1V"
1L"
1r"
0h"
1"#
0v"
0&#
0>#
1>
1L
0u
1##
11#
17
0S
0h
1B"
1P"
1l"
1z"
08#
1/
0?
0M
1[
0o
0p
1<"
1_"
0f"
0$#
02#
1@#
08
1F
1."
0C"
1J"
0Q"
0m"
0{"
1+#
0M#
b10011110100011100111100000111101 *
1L#
b1110101001110011000000011101011 "
b1110101001110011000000011101011 +
1I#
1@
1N
0\
1%#
13#
0A#
19
0U
0j
0/"
1D"
1R"
1n"
1|"
0:#
1N#
1<
1J
0Q
0X
0f
0m
1{
19"
1\"
0c"
1!#
1/#
06#
0=#
14
1B
0P
0e
0z
0*"
1?"
1F"
1M"
1i"
1w"
1'#
05#
1J#
1%
b10010110101010110101100000101101 $
b10010110101010110101100000101101 )
b11011110100011100010100010111101 #
b11011110100011100010100010111101 (
1'
b11010110110010101100100110101101 &
#50000
03"
0-"
1)"
1r
0R
07#
0,"
0D
0L
1u
0)#
01#
0&"
1o"
0>
1o
1>"
1a"
0##
0,
13
1""
1v"
1H
1]
0k
0y
10"
0L"
0S"
1r"
0h"
1-#
0!
1B#
0=
1:
0K
0A
0Y
1O
0V
1n
0|
1A"
07"
1d"
1Z"
1k"
0"#
1}"
00#
0&#
0>#
14#
0;#
0/
16
0%"
0:"
1]"
1l"
1y"
0F#
07
0E
0S
1h
0v
1;"
1^"
1e"
0z"
0*#
08#
0L#
10
1M
1b
1p
0}
0~
04"
15"
1Q"
1W"
1X"
1m"
b1111111110000011000000010 *
1s"
12#
1G#
1M#
1?
0F
1T
0[
0<"
0_"
1$#
0+#
19#
0@#
b10110111011000101110100101101101 "
b10110111011000101110100101101101 +
1I#
0N
0R"
0n"
03#
0H#
0N#
12
09
0@
1j
0x
1="
1`"
1g"
1u"
0|"
0%#
1.
05
0J
1_
1f
1m
0t
0{
0+"
12"
0N"
1U"
1c"
0j"
1q"
0x"
0/#
0D#
0K#
1-
04
0;
0B
1P
0W
1e
0s
1*"
18"
1["
1b"
1p"
0w"
0~"
0'#
15#
0<#
0%
b101011100111000011100001010 $
b101011100111000011100001010 )
b10110001111011110110001001100011 #
b10110001111011110110001001100011 (
b1110101001110011000000011101011 &
#55000
0Z"
0]"
0W"
1S"
0V"
0P"
1L"
0r
0v"
0O"
0u
0y"
0I"
03
1d
0o
1k
0>"
0s"
1E"
1R
0H
1V
00"
17#
0-#
1;#
06
1,
1O
1g
0]
0n
0A"
0r"
1h"
1o"
14#
0B#
1L
0H"
11#
00
1a
0h
0;"
0l"
0M
1[
05"
b10000011000000000000100100000 *
0B"
02#
1@#
11
0T
0b
0m"
1t"
09#
0G#
0M#
b1100101110111000110011011001011 "
b1100101110111000110011011001011 +
1I#
1N
13#
02
1c
0j
0="
0D"
0u"
1J
1X
0f
1+"
02"
09"
0@"
1N"
1/#
1=#
0-
0P
1^
0e
0*"
08"
0?"
0M"
0i"
0p"
05#
0C#
0J#
1%
b1010101011110000100010110101010 $
b1010101011110000100010110101010 )
b10000011001000010000100100000 #
b10000011001000010000100100000 (
0'
b10110111011000101110100101101101 &
